{
  "uri": "https://www.contrataciones.gov.py/datos/record-package/289399.json",
  "publicationPolicy": "https://www.contrataciones.gov.py/datos/legal",
  "license": "https://creativecommons.org/licenses/by/4.0/",
  "publishedDate": "2017-01-04T11:12:50-05:00",
  "records": [
    {
      "releases": [
        {
          "url": "https://www.contrataciones.gov.py/datos/id/planning/289399-contratacion-agencias-transporte-pasajeros-reuniones-congresos-seminarios.json",
          "date": "2015-03-09T17:55:31-04:00",
          "tag": [
            "planning"
          ]
        },
        {
          "url": "https://www.contrataciones.gov.py/datos/id/tender/289399-contratacion-agencias-transporte-pasajeros-reuniones-congresos-seminarios-otros-ad-1.json",
          "date": "2016-01-28T13:54:42-05:00",
          "tag": [
            "tender"
          ]
        },
        {
          "url": "https://www.contrataciones.gov.py/datos/id/award/289399-contratacion-agencias-transporte-pasajeros-reuniones-congresos-seminarios-otros-ad-1.json",
          "date": "2016-03-14T15:28:43-04:00",
          "tag": [
            "award"
          ]
        },
        {
          "url": "https://www.contrataciones.gov.py/datos/id/contract/289399-premier-s-r-l-1.json",
          "date": "2016-03-11T12:00:00-05:00",
          "tag": [
            "contract"
          ]
        }
      ],
      "compiledRelease": {
        "awards": [
          {
            "id": "289399-contratacion-agencias-transporte-pasajeros-reuniones-congresos-seminarios-otros-ad-1",
            "status": "active",
            "suppliers": [
              {
                "address": {
                  "streetAddress": "AYOLAS 630",
                  "countryName": "Paraguay",
                  "region": "Asunción",
                  "postalCode": "",
                  "locality": "ASUNCION"
                },
                "name": "PREMIER S.R.L.",
                "identifier": {
                  "legalName": "PREMIER S.R.L.",
                  "id": "80001145-7",
                  "scheme": "Registro Único de Contribuyente emitido por el Ministerio de Hacienda del Gobierno de Paraguay"
                },
                "contactPoint": {
                  "email": "premier@premierviajes.com.py",
                  "url": "",
                  "name": "LIDIA CONCEPCION FIORE G.",
                  "faxNumber": "",
                  "telephone": "444141-441654-450800"
                }
              }
            ],
            "date": "2016-03-14T15:28:43-04:00",
            "url": "https://www.contrataciones.gov.py/datos/id/adjudicaciones/289399-contratacion-agencias-transporte-pasajeros-reuniones-congresos-seminarios-otros-ad-1",
            "value": {
              "currency": "PYG",
              "amount": 140312000.0
            },
            "title": "Contrataciòn de agencias de transporte de pasajeros a reuniones, congresos, seminarios, y otros - Ad Referéndum 2016"
          }
        ],
        "id": "289399-contratacion-agencias-transporte-pasajeros-reuniones-congresos-seminarios-otros-ad-1",
        "tender": {
          "tenderPeriod": {
            "startDate": null,
            "endDate": "2016-02-03T09:00:00-05:00"
          },
          "id": "289399-contratacion-agencias-transporte-pasajeros-reuniones-congresos-seminarios-otros-ad-1",
          "status": "complete",
          "documents": [
            {
              "id": "heoD%2F1REyYk%3D",
              "language": "es",
              "url": "https://www.contrataciones.gov.py/documentos/download/convocatoria/heoD%252F1REyYk%253D",
              "format": "application/zip",
              "documentType": "Carta de Invitación",
              "title": "Carta de Invitación"
            },
            {
              "id": "zq8PVrXPZNM%3D",
              "language": "es",
              "url": "https://www.contrataciones.gov.py/documentos/download/convocatoria/zq8PVrXPZNM%253D",
              "format": "application/pdf",
              "documentType": "Carta de Invitación",
              "title": "Carta de Invitación"
            },
            {
              "id": "voErWargmpM%3D",
              "language": "es",
              "url": "https://www.contrataciones.gov.py/documentos/download/convocatoria/voErWargmpM%253D",
              "format": "application/pdf",
              "documentType": "Condiciones Generales del Contrato - Bienes y Servicios",
              "title": "Condiciones Generales del Contrato - Bienes y Servicios"
            },
            {
              "id": "V%2FHNYu8Ge%2Fs%3D",
              "language": "es",
              "url": "https://www.contrataciones.gov.py/documentos/download/convocatoria/V%252FHNYu8Ge%252Fs%253D",
              "format": "application/pdf",
              "documentType": "Instrucción a los Oferentes - Bienes y Servicios",
              "title": "Instrucción a los Oferentes - Bienes y Servicios"
            }
          ],
          "items": [
            {
              "classification": {
                "uri": "https://www.contrataciones.gov.py/datos/api/v2/doc/catalogo/nivel-5/78111808-003",
                "scheme": "Catálogo de productos, bienes y servicios de la Dirección Nacional de Contrataciones Públicas del Paraguay",
                "id": "78111808-003",
                "description": "Catálogo de productos, bienes y servicios de la Dirección Nacional de Contrataciones Públicas del Paraguay Nivel 5, basado en UNSPSC"
              },
              "unit": {
                "value": {
                  "currency": "PYG",
                  "amount": null
                },
                "name": "Unidad"
              },
              "id": "Y7E7Czj6PpRg3mM07iELNw%3D%3D",
              "quantity": 1,
              "description": "Alquiler de Bus para traslado de pasajero"
            },
            {
              "classification": {
                "uri": "https://www.contrataciones.gov.py/datos/api/v2/doc/catalogo/nivel-5/78111808-003",
                "scheme": "Catálogo de productos, bienes y servicios de la Dirección Nacional de Contrataciones Públicas del Paraguay",
                "id": "78111808-003",
                "description": "Catálogo de productos, bienes y servicios de la Dirección Nacional de Contrataciones Públicas del Paraguay Nivel 5, basado en UNSPSC"
              },
              "unit": {
                "value": {
                  "currency": "PYG",
                  "amount": null
                },
                "name": "Unidad"
              },
              "id": "c5lX26ps2YJg3mM07iELNw%3D%3D",
              "quantity": 1,
              "description": "Alquiler de Bus para traslado de pasajero"
            },
            {
              "classification": {
                "uri": "https://www.contrataciones.gov.py/datos/api/v2/doc/catalogo/nivel-5/78111808-003",
                "scheme": "Catálogo de productos, bienes y servicios de la Dirección Nacional de Contrataciones Públicas del Paraguay",
                "id": "78111808-003",
                "description": "Catálogo de productos, bienes y servicios de la Dirección Nacional de Contrataciones Públicas del Paraguay Nivel 5, basado en UNSPSC"
              },
              "unit": {
                "value": {
                  "currency": "PYG",
                  "amount": null
                },
                "name": "Unidad"
              },
              "id": "KPCMRtxjBrlg3mM07iELNw%3D%3D",
              "quantity": 1,
              "description": "Alquiler de Bus para traslado de pasajero"
            },
            {
              "classification": {
                "uri": "https://www.contrataciones.gov.py/datos/api/v2/doc/catalogo/nivel-5/78111808-003",
                "scheme": "Catálogo de productos, bienes y servicios de la Dirección Nacional de Contrataciones Públicas del Paraguay",
                "id": "78111808-003",
                "description": "Catálogo de productos, bienes y servicios de la Dirección Nacional de Contrataciones Públicas del Paraguay Nivel 5, basado en UNSPSC"
              },
              "unit": {
                "value": {
                  "currency": "PYG",
                  "amount": null
                },
                "name": "Unidad"
              },
              "id": "qr3vQLdBrvlg3mM07iELNw%3D%3D",
              "quantity": 1,
              "description": "Alquiler de Bus para traslado de pasajero"
            },
            {
              "classification": {
                "uri": "https://www.contrataciones.gov.py/datos/api/v2/doc/catalogo/nivel-5/78111808-003",
                "scheme": "Catálogo de productos, bienes y servicios de la Dirección Nacional de Contrataciones Públicas del Paraguay",
                "id": "78111808-003",
                "description": "Catálogo de productos, bienes y servicios de la Dirección Nacional de Contrataciones Públicas del Paraguay Nivel 5, basado en UNSPSC"
              },
              "unit": {
                "value": {
                  "currency": "PYG",
                  "amount": null
                },
                "name": "Unidad"
              },
              "id": "E7FMW7UFQFtg3mM07iELNw%3D%3D",
              "quantity": 1,
              "description": "Alquiler de Bus para traslado de pasajero"
            },
            {
              "classification": {
                "uri": "https://www.contrataciones.gov.py/datos/api/v2/doc/catalogo/nivel-5/78111808-003",
                "scheme": "Catálogo de productos, bienes y servicios de la Dirección Nacional de Contrataciones Públicas del Paraguay",
                "id": "78111808-003",
                "description": "Catálogo de productos, bienes y servicios de la Dirección Nacional de Contrataciones Públicas del Paraguay Nivel 5, basado en UNSPSC"
              },
              "unit": {
                "value": {
                  "currency": "PYG",
                  "amount": null
                },
                "name": "Unidad"
              },
              "id": "zCQ2Rw5%2FaHVg3mM07iELNw%3D%3D",
              "quantity": 1,
              "description": "Alquiler de Bus para traslado de pasajero"
            },
            {
              "classification": {
                "uri": "https://www.contrataciones.gov.py/datos/api/v2/doc/catalogo/nivel-5/78111808-003",
                "scheme": "Catálogo de productos, bienes y servicios de la Dirección Nacional de Contrataciones Públicas del Paraguay",
                "id": "78111808-003",
                "description": "Catálogo de productos, bienes y servicios de la Dirección Nacional de Contrataciones Públicas del Paraguay Nivel 5, basado en UNSPSC"
              },
              "unit": {
                "value": {
                  "currency": "PYG",
                  "amount": null
                },
                "name": "Unidad"
              },
              "id": "X%2B2a%2B52XtYFg3mM07iELNw%3D%3D",
              "quantity": 1,
              "description": "Alquiler de Bus para traslado de pasajero"
            },
            {
              "classification": {
                "uri": "https://www.contrataciones.gov.py/datos/api/v2/doc/catalogo/nivel-5/78111808-003",
                "scheme": "Catálogo de productos, bienes y servicios de la Dirección Nacional de Contrataciones Públicas del Paraguay",
                "id": "78111808-003",
                "description": "Catálogo de productos, bienes y servicios de la Dirección Nacional de Contrataciones Públicas del Paraguay Nivel 5, basado en UNSPSC"
              },
              "unit": {
                "value": {
                  "currency": "PYG",
                  "amount": null
                },
                "name": "Unidad"
              },
              "id": "VxdOnepe9NBg3mM07iELNw%3D%3D",
              "quantity": 1,
              "description": "Alquiler de Bus para traslado de pasajero"
            },
            {
              "classification": {
                "uri": "https://www.contrataciones.gov.py/datos/api/v2/doc/catalogo/nivel-5/78111808-003",
                "scheme": "Catálogo de productos, bienes y servicios de la Dirección Nacional de Contrataciones Públicas del Paraguay",
                "id": "78111808-003",
                "description": "Catálogo de productos, bienes y servicios de la Dirección Nacional de Contrataciones Públicas del Paraguay Nivel 5, basado en UNSPSC"
              },
              "unit": {
                "value": {
                  "currency": "PYG",
                  "amount": null
                },
                "name": "Unidad"
              },
              "id": "iczi3MzHqglg3mM07iELNw%3D%3D",
              "quantity": 1,
              "description": "Alquiler de Bus para traslado de pasajero"
            },
            {
              "classification": {
                "uri": "https://www.contrataciones.gov.py/datos/api/v2/doc/catalogo/nivel-5/78111808-003",
                "scheme": "Catálogo de productos, bienes y servicios de la Dirección Nacional de Contrataciones Públicas del Paraguay",
                "id": "78111808-003",
                "description": "Catálogo de productos, bienes y servicios de la Dirección Nacional de Contrataciones Públicas del Paraguay Nivel 5, basado en UNSPSC"
              },
              "unit": {
                "value": {
                  "currency": "PYG",
                  "amount": null
                },
                "name": "Unidad"
              },
              "id": "riZ5UmUYhBRg3mM07iELNw%3D%3D",
              "quantity": 1,
              "description": "Alquiler de Bus para traslado de pasajero"
            },
            {
              "classification": {
                "uri": "https://www.contrataciones.gov.py/datos/api/v2/doc/catalogo/nivel-5/78111808-003",
                "scheme": "Catálogo de productos, bienes y servicios de la Dirección Nacional de Contrataciones Públicas del Paraguay",
                "id": "78111808-003",
                "description": "Catálogo de productos, bienes y servicios de la Dirección Nacional de Contrataciones Públicas del Paraguay Nivel 5, basado en UNSPSC"
              },
              "unit": {
                "value": {
                  "currency": "PYG",
                  "amount": null
                },
                "name": "Unidad"
              },
              "id": "IfN5lmEUiMxg3mM07iELNw%3D%3D",
              "quantity": 1,
              "description": "Alquiler de Bus para traslado de pasajero"
            },
            {
              "classification": {
                "uri": "https://www.contrataciones.gov.py/datos/api/v2/doc/catalogo/nivel-5/78111808-003",
                "scheme": "Catálogo de productos, bienes y servicios de la Dirección Nacional de Contrataciones Públicas del Paraguay",
                "id": "78111808-003",
                "description": "Catálogo de productos, bienes y servicios de la Dirección Nacional de Contrataciones Públicas del Paraguay Nivel 5, basado en UNSPSC"
              },
              "unit": {
                "value": {
                  "currency": "PYG",
                  "amount": null
                },
                "name": "Unidad"
              },
              "id": "dDZLdvXtLPNg3mM07iELNw%3D%3D",
              "quantity": 1,
              "description": "Alquiler de Bus para traslado de pasajero"
            }
          ],
          "submissionMethod": [
            "written"
          ],
          "url": "https://www.contrataciones.gov.py/datos/id/convocatorias/289399-contratacion-agencias-transporte-pasajeros-reuniones-congresos-seminarios-otros-ad-1",
          "value": {
            "currency": "PYG",
            "amount": null
          },
          "lots": [
            {
              "id": "XQ7EE6b2rh4%3D",
              "items": [
                "Y7E7Czj6PpRg3mM07iELNw%3D%3D",
                "c5lX26ps2YJg3mM07iELNw%3D%3D",
                "KPCMRtxjBrlg3mM07iELNw%3D%3D",
                "qr3vQLdBrvlg3mM07iELNw%3D%3D",
                "E7FMW7UFQFtg3mM07iELNw%3D%3D",
                "zCQ2Rw5%2FaHVg3mM07iELNw%3D%3D",
                "X%2B2a%2B52XtYFg3mM07iELNw%3D%3D",
                "VxdOnepe9NBg3mM07iELNw%3D%3D",
                "iczi3MzHqglg3mM07iELNw%3D%3D",
                "riZ5UmUYhBRg3mM07iELNw%3D%3D",
                "IfN5lmEUiMxg3mM07iELNw%3D%3D",
                "dDZLdvXtLPNg3mM07iELNw%3D%3D"
              ],
              "title": "Contrataciòn de agencias de transporte de pasajeros a reuniones, congresos, seminarios, y otros - Ad Referéndum 2016"
            }
          ],
          "title": "Contrataciòn de agencias de transporte de pasajeros a reuniones, congresos, seminarios, y otros - Ad Referéndum 2016",
          "awardPeriod": {
            "endDate": null,
            "startDate": "2016-01-29T10:00:00-05:00"
          },
          "procuringEntity": {
            "name": "Facultad Politecnica / Universidad Nacional de Asunción",
            "contactPoint": {
              "email": "uoc.fpuna@gmail.com",
              "name": "Téc. Delia Raquel Abreu",
              "telephone": "5887145"
            }
          },
          "hasEnquiries": false,
          "enquiryPeriod": {
            "endDate": "2016-01-29T10:00:00-05:00"
          }
        },
        "tag": [
          "compiled"
        ],
        "planning": {
          "url": "https://www.contrataciones.gov.py/datos/id/planificaciones/289399-contratacion-agencias-transporte-pasajeros-reuniones-congresos-seminarios",
          "budget": {
            "amount": {
              "currency": "PYG",
              "amount": null
            },
            "description": "Contrataciòn de agencias de transporte de pasajeros a reuniones, congresos, seminarios, y otros - Ad Referéndum 2016"
          }
        },
        "language": "es",
        "initiationType": "tender",
        "date": "2017-01-04T11:12:50-05:00",
        "contract": [
          {
            "id": "289399-premier-s-r-l-1",
            "status": "active",
            "dateSigned": "2016-03-11T12:00:00-05:00",
            "documents": [
              {
                "id": "CNly5pt3dXg%3D",
                "language": "es",
                "url": "https://www.contrataciones.gov.py/documentos/download/adjudicacion/CNly5pt3dXg%253D",
                "format": "application/pdf",
                "documentType": "Acta de Apertura",
                "title": "Acta de Apertura"
              },
              {
                "id": "klcBhBksNQU%3D",
                "language": "es",
                "url": "https://www.contrataciones.gov.py/documentos/download/adjudicacion/klcBhBksNQU%253D",
                "format": "application/pdf",
                "documentType": "Cuadro Comparativo de Ofertas",
                "title": "Cuadro Comparativo de Ofertas"
              },
              {
                "id": "%2BmcSjGBFkRs%3D",
                "language": "es",
                "url": "https://www.contrataciones.gov.py/documentos/download/adjudicacion/%252BmcSjGBFkRs%253D",
                "format": "application/pdf",
                "documentType": "evaluationReports",
                "title": "Informe de Evaluación"
              },
              {
                "id": "E9YSs3uggKg%3D",
                "language": "es",
                "url": "https://www.contrataciones.gov.py/documentos/download/adjudicacion/E9YSs3uggKg%253D",
                "format": "application/pdf",
                "documentType": "Notificación al Oferente",
                "title": "Notificación al Oferente"
              },
              {
                "id": "WlmZU%2BWbq1U%3D",
                "language": "es",
                "url": "https://www.contrataciones.gov.py/documentos/download/adjudicacion/WlmZU%252BWbq1U%253D",
                "format": "application/pdf",
                "documentType": "Orden de Compra o Contrato",
                "title": "Orden de Compra o Contrato"
              },
              {
                "id": "GbdA9f92Ne8%3D",
                "language": "es",
                "url": "https://www.contrataciones.gov.py/documentos/download/adjudicacion/GbdA9f92Ne8%253D",
                "format": "application/pdf",
                "documentType": "awardNotice",
                "title": "Resolución de Adjudicación"
              }
            ],
            "period": {
              "startDate": "",
              "endDate": ""
            },
            "awardID": "289399-contratacion-agencias-transporte-pasajeros-reuniones-congresos-seminarios-otros-ad-1",
            "url": "https://www.contrataciones.gov.py/datos/id/contratos/289399-premier-s-r-l-1",
            "value": {
              "currency": "PYG",
              "amount": 140312000.0
            },
            "lots": [
              {
                "id": "WkBpn7BUu80%3D",
                "items": [
                  "zo59DlirPk0%3D",
                  "v%2FCpWkx2F6E%3D",
                  "MPtVP0mbv4o%3D",
                  "f%2FoKZdyOGW4%3D",
                  "BXR6osuociY%3D",
                  "GnvNsnElnBQ%3D",
                  "viIcKiF54MQ%3D",
                  "aeDLGDw74WY%3D",
                  "wtFMcJApQeU%3D",
                  "%2FvmnXGVhxrA%3D",
                  "2uvIjzxanAw%3D",
                  "4tLB%2Bs7ece4%3D"
                ],
                "title": "Contrataciòn de agencias de transporte de pasajeros a reuniones, congresos, seminarios, y otros - Ad Referéndum 2016"
              }
            ],
            "items": [
              {
                "classification": {
                  "uri": "https://www.contrataciones.gov.py/datos/api/v2/doc/catalogo/nivel-5/78111808-003",
                  "id": "78111808-003",
                  "description": "Catálogo de productos, bienes y servicios de la Dirección Nacional de Contrataciones Públicas del Paraguay Nivel 5, basado en UNSPSC",
                  "schema": "Catálogo de productos, bienes y servicios de la Dirección Nacional de Contrataciones Públicas del Paraguay"
                },
                "unit": {
                  "value": {
                    "currency": "PYG",
                    "amount": "_NO_APLICA_"
                  },
                  "name": "_NO_APLICA_"
                },
                "id": "zo59DlirPk0%3D",
                "quantity": "_NO_APLICA_",
                "description": "Alquiler de Bus para traslado de pasajero"
              },
              {
                "classification": {
                  "uri": "https://www.contrataciones.gov.py/datos/api/v2/doc/catalogo/nivel-5/78111808-003",
                  "id": "78111808-003",
                  "description": "Catálogo de productos, bienes y servicios de la Dirección Nacional de Contrataciones Públicas del Paraguay Nivel 5, basado en UNSPSC",
                  "schema": "Catálogo de productos, bienes y servicios de la Dirección Nacional de Contrataciones Públicas del Paraguay"
                },
                "unit": {
                  "value": {
                    "currency": "PYG",
                    "amount": "_NO_APLICA_"
                  },
                  "name": "_NO_APLICA_"
                },
                "id": "v%2FCpWkx2F6E%3D",
                "quantity": "_NO_APLICA_",
                "description": "Alquiler de Bus para traslado de pasajero"
              },
              {
                "classification": {
                  "uri": "https://www.contrataciones.gov.py/datos/api/v2/doc/catalogo/nivel-5/78111808-003",
                  "id": "78111808-003",
                  "description": "Catálogo de productos, bienes y servicios de la Dirección Nacional de Contrataciones Públicas del Paraguay Nivel 5, basado en UNSPSC",
                  "schema": "Catálogo de productos, bienes y servicios de la Dirección Nacional de Contrataciones Públicas del Paraguay"
                },
                "unit": {
                  "value": {
                    "currency": "PYG",
                    "amount": "_NO_APLICA_"
                  },
                  "name": "_NO_APLICA_"
                },
                "id": "MPtVP0mbv4o%3D",
                "quantity": "_NO_APLICA_",
                "description": "Alquiler de Bus para traslado de pasajero"
              },
              {
                "classification": {
                  "uri": "https://www.contrataciones.gov.py/datos/api/v2/doc/catalogo/nivel-5/78111808-003",
                  "id": "78111808-003",
                  "description": "Catálogo de productos, bienes y servicios de la Dirección Nacional de Contrataciones Públicas del Paraguay Nivel 5, basado en UNSPSC",
                  "schema": "Catálogo de productos, bienes y servicios de la Dirección Nacional de Contrataciones Públicas del Paraguay"
                },
                "unit": {
                  "value": {
                    "currency": "PYG",
                    "amount": "_NO_APLICA_"
                  },
                  "name": "_NO_APLICA_"
                },
                "id": "f%2FoKZdyOGW4%3D",
                "quantity": "_NO_APLICA_",
                "description": "Alquiler de Bus para traslado de pasajero"
              },
              {
                "classification": {
                  "uri": "https://www.contrataciones.gov.py/datos/api/v2/doc/catalogo/nivel-5/78111808-003",
                  "id": "78111808-003",
                  "description": "Catálogo de productos, bienes y servicios de la Dirección Nacional de Contrataciones Públicas del Paraguay Nivel 5, basado en UNSPSC",
                  "schema": "Catálogo de productos, bienes y servicios de la Dirección Nacional de Contrataciones Públicas del Paraguay"
                },
                "unit": {
                  "value": {
                    "currency": "PYG",
                    "amount": "_NO_APLICA_"
                  },
                  "name": "_NO_APLICA_"
                },
                "id": "BXR6osuociY%3D",
                "quantity": "_NO_APLICA_",
                "description": "Alquiler de Bus para traslado de pasajero"
              },
              {
                "classification": {
                  "uri": "https://www.contrataciones.gov.py/datos/api/v2/doc/catalogo/nivel-5/78111808-003",
                  "id": "78111808-003",
                  "description": "Catálogo de productos, bienes y servicios de la Dirección Nacional de Contrataciones Públicas del Paraguay Nivel 5, basado en UNSPSC",
                  "schema": "Catálogo de productos, bienes y servicios de la Dirección Nacional de Contrataciones Públicas del Paraguay"
                },
                "unit": {
                  "value": {
                    "currency": "PYG",
                    "amount": "_NO_APLICA_"
                  },
                  "name": "_NO_APLICA_"
                },
                "id": "GnvNsnElnBQ%3D",
                "quantity": "_NO_APLICA_",
                "description": "Alquiler de Bus para traslado de pasajero"
              },
              {
                "classification": {
                  "uri": "https://www.contrataciones.gov.py/datos/api/v2/doc/catalogo/nivel-5/78111808-003",
                  "id": "78111808-003",
                  "description": "Catálogo de productos, bienes y servicios de la Dirección Nacional de Contrataciones Públicas del Paraguay Nivel 5, basado en UNSPSC",
                  "schema": "Catálogo de productos, bienes y servicios de la Dirección Nacional de Contrataciones Públicas del Paraguay"
                },
                "unit": {
                  "value": {
                    "currency": "PYG",
                    "amount": "_NO_APLICA_"
                  },
                  "name": "_NO_APLICA_"
                },
                "id": "viIcKiF54MQ%3D",
                "quantity": "_NO_APLICA_",
                "description": "Alquiler de Bus para traslado de pasajero"
              },
              {
                "classification": {
                  "uri": "https://www.contrataciones.gov.py/datos/api/v2/doc/catalogo/nivel-5/78111808-003",
                  "id": "78111808-003",
                  "description": "Catálogo de productos, bienes y servicios de la Dirección Nacional de Contrataciones Públicas del Paraguay Nivel 5, basado en UNSPSC",
                  "schema": "Catálogo de productos, bienes y servicios de la Dirección Nacional de Contrataciones Públicas del Paraguay"
                },
                "unit": {
                  "value": {
                    "currency": "PYG",
                    "amount": "_NO_APLICA_"
                  },
                  "name": "_NO_APLICA_"
                },
                "id": "aeDLGDw74WY%3D",
                "quantity": "_NO_APLICA_",
                "description": "Alquiler de Bus para traslado de pasajero"
              },
              {
                "classification": {
                  "uri": "https://www.contrataciones.gov.py/datos/api/v2/doc/catalogo/nivel-5/78111808-003",
                  "id": "78111808-003",
                  "description": "Catálogo de productos, bienes y servicios de la Dirección Nacional de Contrataciones Públicas del Paraguay Nivel 5, basado en UNSPSC",
                  "schema": "Catálogo de productos, bienes y servicios de la Dirección Nacional de Contrataciones Públicas del Paraguay"
                },
                "unit": {
                  "value": {
                    "currency": "PYG",
                    "amount": "_NO_APLICA_"
                  },
                  "name": "_NO_APLICA_"
                },
                "id": "wtFMcJApQeU%3D",
                "quantity": "_NO_APLICA_",
                "description": "Alquiler de Bus para traslado de pasajero"
              },
              {
                "classification": {
                  "uri": "https://www.contrataciones.gov.py/datos/api/v2/doc/catalogo/nivel-5/78111808-003",
                  "id": "78111808-003",
                  "description": "Catálogo de productos, bienes y servicios de la Dirección Nacional de Contrataciones Públicas del Paraguay Nivel 5, basado en UNSPSC",
                  "schema": "Catálogo de productos, bienes y servicios de la Dirección Nacional de Contrataciones Públicas del Paraguay"
                },
                "unit": {
                  "value": {
                    "currency": "PYG",
                    "amount": "_NO_APLICA_"
                  },
                  "name": "_NO_APLICA_"
                },
                "id": "%2FvmnXGVhxrA%3D",
                "quantity": "_NO_APLICA_",
                "description": "Alquiler de Bus para traslado de pasajero"
              },
              {
                "classification": {
                  "uri": "https://www.contrataciones.gov.py/datos/api/v2/doc/catalogo/nivel-5/78111808-003",
                  "id": "78111808-003",
                  "description": "Catálogo de productos, bienes y servicios de la Dirección Nacional de Contrataciones Públicas del Paraguay Nivel 5, basado en UNSPSC",
                  "schema": "Catálogo de productos, bienes y servicios de la Dirección Nacional de Contrataciones Públicas del Paraguay"
                },
                "unit": {
                  "value": {
                    "currency": "PYG",
                    "amount": "_NO_APLICA_"
                  },
                  "name": "_NO_APLICA_"
                },
                "id": "2uvIjzxanAw%3D",
                "quantity": "_NO_APLICA_",
                "description": "Alquiler de Bus para traslado de pasajero"
              },
              {
                "classification": {
                  "uri": "https://www.contrataciones.gov.py/datos/api/v2/doc/catalogo/nivel-5/78111808-003",
                  "id": "78111808-003",
                  "description": "Catálogo de productos, bienes y servicios de la Dirección Nacional de Contrataciones Públicas del Paraguay Nivel 5, basado en UNSPSC",
                  "schema": "Catálogo de productos, bienes y servicios de la Dirección Nacional de Contrataciones Públicas del Paraguay"
                },
                "unit": {
                  "value": {
                    "currency": "PYG",
                    "amount": "_NO_APLICA_"
                  },
                  "name": "_NO_APLICA_"
                },
                "id": "4tLB%2Bs7ece4%3D",
                "quantity": "_NO_APLICA_",
                "description": "Alquiler de Bus para traslado de pasajero"
              }
            ],
            "suppliers": {
              "name": "PREMIER S.R.L.",
              "identifier": {
                "legalName": "PREMIER S.R.L.",
                "id": "80001145-7",
                "scheme": "Registro Único de Contribuyente emitido por el Ministerio de Hacienda del Gobierno de Paraguay"
              },
              "identifiers": {
                "key": "289399-premier-s-r-l-1"
              }
            },
            "dncpContractCode": "CD-28001-16-119312",
            "title": "Contrataciòn de agencias de transporte de pasajeros a reuniones, congresos, seminarios, y otros - Ad Referéndum 2016"
          }
        ],
        "ocid": "ocds-03ad3f-289399",
        "buyer": {
          "name": "Facultad Politecnica / Universidad Nacional de Asunción",
          "contactPoint": {
            "email": "uoc.fpuna@gmail.com",
            "name": "Téc. Delia Raquel Abreu",
            "telephone": "5887145"
          }
        }
      },
      "ocid": "ocds-03ad3f-289399"
    }
  ],
  "packages": [
    "https://www.contrataciones.gov.py/datos/id/planning/289399-contratacion-agencias-transporte-pasajeros-reuniones-congresos-seminarios.json",
    "https://www.contrataciones.gov.py/datos/id/tender/289399-contratacion-agencias-transporte-pasajeros-reuniones-congresos-seminarios-otros-ad-1.json",
    "https://www.contrataciones.gov.py/datos/id/award/289399-contratacion-agencias-transporte-pasajeros-reuniones-congresos-seminarios-otros-ad-1.json",
    "https://www.contrataciones.gov.py/datos/id/contract/289399-premier-s-r-l-1.json"
  ],
  "publisher": {
    "legalName": "Dirección Nacional de Contrataciones Públicas, Paraguay",
    "uri": "https://contrataciones.gov.py/datos",
    "name": "DNCP - Paraguay"
  }
}