{
  "ocid": "ocds-gyl66f-borbda-2wlmoa",
  "id": "ocds-gyl66f-borbda-2wlmoa",
  "date": "2014-10-20T00:00:00Z",
  "language": "EN",
  "tag": [
    "contract"
  ],
  "initiationType": "tender",
  "parties": [
    {
      "identifier": {
        "id": "27089502",
        "legalName": "benin-owena river basin development authority",
        "scheme": "NGA-BRBDA"
      },
      "name": "benin-owena river basin development authority",
      "roles": [
        "buyer"
      ],
      "id": "NGA-BRBDA-27089502"
    },
    {
      "additionalIdentifiers": [
        {
          "id": "42469649",
          "legalName": "benin-owena river basin development authority",
          "scheme": "NGA-BRBDA"
        }
      ],
      "address": {
        "countryName": "Nigeria"
      },
      "contactPoint": {},
      "identifier": {
        "id": "02143276",
        "legalName": "benin-owena river basin development authority",
        "scheme": "NGA-BRBDA"
      },
      "name": "benin-owena river basin development authority",
      "roles": [
        "procuringEntity"
      ],
      "id": "NGA-BRBDA-02143276"
    },
    {
      "address": {},
      "contactPoint": {},
      "identifier": {
        "id": "0510979101",
        "scheme": "NGA-BPPNO"
      },
      "roles": [
        "tenderer"
      ],
      "id": "NGA-BPPNO-0510979101"
    },
    {
      "additionalIdentifiers": [
        {
          "legalName": "FIC Consultant Limited"
        }
      ],
      "identifier": {
        "id": "04011010",
        "legalName": "fic consultant limited",
        "scheme": "NGA-FCL"
      },
      "name": "fic consultant limited",
      "roles": [
        "supplier"
      ],
      "id": "NGA-FCL-04011010"
    }
  ],
  "awards": [
    {
      "date": "2014-10-20T00:00:00Z",
      "description": "Part payment for the supervision of Construction of Irrigation Facilities at Erusu Arigidi Earth Dam.",
      "id": "ocds-gyl66f-borbda-2wlmoa",
      "items": [
        {
          "classification": {
            "id": "13470098",
            "scheme": "CPV"
          },
          "id": "ocds-gyl66f-borbda-2wlmoa-award-item",
          "quantity": 1,
          "unit": {
            "name": "Items",
            "value": {
              "amount": 0,
              "currency": "NGN"
            }
          }
        }
      ],
      "status": "active",
      "suppliers": [
        {
          "id": "NGA-FCL-04011010",
          "name": "fic consultant limited"
        }
      ],
      "title": "Part payment for the supervision of Construction of Irrigation Facilities at Erusu Arigidi Earth Dam.",
      "value": {
        "amount": 2811492.0,
        "currency": "NGN"
      }
    }
  ],
  "buyer": {
    "id": "NGA-BRBDA-27089502",
    "name": "benin-owena river basin development authority"
  },
  "contracts": [
    {
      "awardID": "ocds-gyl66f-borbda-2wlmoa-award",
      "description": "Part payment for the supervision of Construction of Irrigation Facilities at Erusu Arigidi Earth Dam.",
      "documents": [
        {
          "id": "ocds-gyl66f-borbda-2wlmoa",
          "language": "EN"
        }
      ],
      "id": "ocds-gyl66f-borbda-2wlmoa",
      "implementation": {
        "documents": [
          {
            "id": "ocds-gyl66f-borbda-2wlmoa",
            "language": "EN"
          }
        ],
        "milestones": [
          {
            "dateModified": "2014-10-20T00:00:00Z",
            "description": "1.0",
            "documents": [
              {
                "id": "ocds-gyl66f-borbda-2wlmoa-contract-implementation-document",
                "language": "EN"
              }
            ],
            "dueDate": "2014-10-20T00:00:00Z",
            "id": "ocds-gyl66f-borbda-2wlmoa",
            "status": "met",
            "title": "part payment for the supervision of construction of irrigation facilities at erusu arigidi earth dam.-implementation-progress"
          }
        ],
        "transactions": [
          {
            "amount": {
              "amount": 2811492.0,
              "currency": "NGN"
            },
            "date": "2014-10-20T00:00:00Z",
            "id": "ocds-gyl66f-borbda-2wlmoa-nga-contract-transactions-068310727",
            "providerOrganization": {
              "id": "3210104188",
              "legalName": "benin-owena river basin development authority",
              "scheme": "NGN-BRBDA"
            },
            "payer": {
              "id": "NGN-BRBDA-3210104188",
              "name": "benin-owena river basin development authority"
            }
          }
        ]
      },
      "items": [
        {
          "classification": {
            "id": "60337608",
            "scheme": "CPV"
          },
          "id": "ocds-gyl66f-borbda-2wlmoa",
          "quantity": 1,
          "unit": {
            "name": "ocds-gyl66f-borbda-2wlmoa-unit-item",
            "value": {
              "amount": 0,
              "currency": "NGN"
            }
          }
        }
      ],
      "period": {
        "endDate": "2014-12-15T00:00:00Z",
        "startDate": null
      },
      "status": "active",
      "title": "Part Payment For The Supervision Of Construction Of Irrigation Facilities At Erusu Arigidi Earth Dam.",
      "value": {
        "amount": 2811492.0,
        "currency": "NGN"
      }
    }
  ],
  "planning": {
    "budget": {
      "description": "Part Payment For The Supervision Of Construction Of Irrigation Facilities At Erusu Arigidi Earth Dam.",
      "id": "ocds-gyl66f-borbda-2wlmoa",
      "project": "Part Payment For The Supervision Of Construction Of Irrigation Facilities At Erusu Arigidi Earth Dam.",
      "value": {
        "amount": 50000000.0,
        "currency": "NGN"
      }
    },
    "documents": [
      {
        "id": "ocds-gyl66f-borbda-2wlmoa",
        "language": "EN"
      }
    ]
  },
  "tender": {
    "awardPeriod": {
      "endDate": "2014-10-20T00:00:00Z",
      "startDate": "2014-10-20T00:00:00Z"
    },
    "description": "part payment for the supervision of construction of irrigation facilities at erusu arigidi earth dam.",
    "documents": [
      {
        "id": "ocds-gyl66f-borbda-2wlmoa",
        "language": "EN"
      }
    ],
    "enquiryPeriod": {
      "endDate": "2014-08-21T00:00:00Z",
      "startDate": "2014-06-30T00:00:00Z"
    },
    "hasEnquiries": false,
    "id": "ocds-gyl66f-borbda-2wlmoa",
    "items": [
      {
        "classification": {
          "id": "13470098",
          "scheme": "CPV"
        },
        "deliveryAddress": {},
        "deliveryLocation": {
          "gazetteer": {
            "identifiers": [
              "2640729"
            ],
            "scheme": "GEONAMES"
          },
          "geometry": {
            "coordinates": [
              51.751944,
              -1.257778
            ],
            "type": "Point"
          }
        },
        "id": "ocds-gyl66f-borbda-2wlmoa-tender-item-13470098",
        "quantity": 1,
        "unit": {
          "value": {
            "amount": 2811492.0,
            "currency": "NGN"
          }
        }
      }
    ],
    "milestones": [
      {
        "dateModified": "2014-10-20T00:00:00Z",
        "description": "Part Payment For The Supervision Of Construction Of Irrigation Facilities At Erusu Arigidi Earth Dam.",
        "documents": [
          {
            "id": "ocds-gyl66f-borbda-2wlmoa",
            "language": "EN"
          }
        ],
        "dueDate": "2014-10-20T00:00:00Z",
        "id": "ocds-gyl66f-borbda-2wlmoa",
        "status": "met",
        "title": "Part Payment For The Supervision Of Construction Of Irrigation Facilities At Erusu Arigidi Earth Dam."
      }
    ],
    "procurementMethod": "open",
    "procuringEntity": {
      "id": "NGA-BRBDA-02143276",
      "name": "benin-owena river basin development authority"
    },
    "status": "complete",
    "tenderPeriod": {
      "endDate": "2014-08-21T00:00:00Z",
      "startDate": "2014-06-30T00:00:00Z"
    },
    "tenderers": [
      {
        "id": "NGA-BPPNO-0510979101",
        "name": ""
      }
    ],
    "title": "part payment for the supervision of construction of irrigation facilities at erusu arigidi earth dam.",
    "value": {
      "amount": 2811492.0,
      "currency": "NGN"
    }
  },
  "packageInfo": {
    "uri": "http:nigeriaoc.org/open_api",
    "publishedDate": "2017-06-29T19:07:56Z",
    "publisher": {
      "name": "Public Bureau of Procurement",
      "scheme": "NGA-COH",
      "uri": "http://www.bpp.gov.ng"
    }
  },
  "version": "1.1",
  "validationErrors": "properties/tender/properties/tenderers/items/properties/name/minLength: '' is too short"
}