{
  "publisher": {
    "scheme": "GB-GOVUK-crown_comercial_service", 
    "name": "Metropolitan Housing Trust Limited", 
    "uri": "https://www.contractsfinder.service.gov.uk", 
    "uid": null
  }, 
  "license": "https://www.nationalarchives.gov.uk/doc/open-government-licence/version/2/", 
  "publicationPolicy": "https://www.contractsfinder.service.gov.uk", 
  "releases": [
    {
      "language": "en-GB", 
      "buyer": {
        "contactPoint": {
          "telephone": "", 
          "faxNumber": null, 
          "name": "Joanna Anderson", 
          "email": ""
        }, 
        "identifier": {
          "scheme": "", 
          "id": "", 
          "uri": null, 
          "legalName": null
        }, 
        "name": "Metropolitan Housing Trust Limited", 
        "address": {
          "postalCode": null, 
          "countryName": null, 
          "streetAddress": null, 
          "region": null, 
          "locality": null
        }
      }, 
      "ocid": "ocds-b5fd17-371010f3-adc8-11e6-9901-0019b9f3037b", 
      "initiationType": "tender", 
      "tender": {
        "status": "unsuccessful", 
        "procurementMethod": null, 
        "eligibilityCriteria": null, 
        "xClassifications": {
          "isSuitableForVco": false, 
          "ojeuContractType": "Works", 
          "isSuitableForSme": false
        }, 
        "description": "'Metropolitan has sites located within the boroughs of City of Nottingham, Rushcliffe District, Gedling District, Mansfield District, Ashfield District, City of Leicester, Charnwood District, Oadby and Wigston District and South Keveston District. The concentration of the stock consists of medium/low rise flats, houses, sheltered accommodation, shared ownership, general needs and Leasehold.'", 
        "title": "United Kingdom-Southgate: Pest-control services", 
        "submissionMethodDetails": "Please apply directly to the buyer using the contact details provided.", 
        "items": [
          {
            "id": 1, 
            "classification": {
              "scheme": "CPV", 
              "id": "90922000", 
              "uri": "http://cpv.data.ac.uk/code-90922000.html", 
              "description": "Pest-control services"
            }, 
            "description": "See description of related tender."
          }
        ], 
        "awardCriteriaDetails": null, 
        "value": {
          "currency": "GBP", 
          "amount": null
        }, 
        "minValue": {
          "currency": "GBP", 
          "amount": 88000
        }, 
        "milestones": [
          {
            "status": null, 
            "description": "Anticipated contract start date", 
            "title": "Contract start", 
            "dateModified": null, 
            "id": 1, 
            "dueDate": null
          }, 
          {
            "status": null, 
            "description": "Anticipated contract end date", 
            "title": "Contract end", 
            "dateModified": null, 
            "id": 2, 
            "dueDate": null
          }
        ], 
        "awardCriteria": null, 
        "procurementMethodRationale": null, 
        "submissionMethod": null, 
        "hasEnquiries": null, 
        "id": "ocds-b5fd17-371010f3-adc8-11e6-9901-0019b9f3037b-2015/s-21-34127", 
        "tenderPeriod": {
          "startDate": "2015-11-04T00:00:00Z", 
          "endDate": "2019-11-04T00:00:00Z"
        }
      }, 
      "tag": [
        "tender"
      ], 
      "date": "2015-02-10T23:44:29Z", 
      "id": "ocds-b5fd17-371010f3-adc8-11e6-9901-0019b9f3037b-2015-s-21-34127"
    }
  ], 
  "publishedDate": "2015-02-10T23:44:29Z", 
  "uri": "https://www.contractsfinder.service.gov.uk/Published/Notice/releases/ae4f525f-e29c-49a1-a5e8-072730864c3b.json"
}