{
  "publisher": {
    "documentation_en": "https://buyandsell.gc.ca/procurement-data/open-contracting-data-standard-pilot/download-ocds-pilot-data", 
    "documentation_fr": "https://achatsetventes.gc.ca/donnees-sur-l-approvisionnement/projet-pilote-norme-relative-aux-donnees-sur-la-passation-de-marches-ouverts/telecharger-les-donnees-du-projet-pilote-ndpmo", 
    "name": "Buyandsell.gc.ca - Achatsetventes.gc.ca", 
    "uri_en": "https://buyandsell.gc.ca", 
    "uri_fr": "https://achatsetventes.gc.ca"
  }, 
  "versionedRelease": {
    "language": [
      {
        "releaseDate": "2015-10-29T17:47:12Z", 
        "releaseID": "01044-140631/001/XL", 
        "releaseTag": [
          "compiled"
        ], 
        "value": "en"
      }
    ], 
    "contracts": [
      {
        "status": [
          {
            "releaseDate": "2015-10-29T17:47:12Z", 
            "releaseID": "01044-140631/001/XL", 
            "releaseTag": [
              "compiled"
            ], 
            "value": "active"
          }
        ], 
        "amendment": {
          "date": [
            {
              "releaseDate": "2015-10-29T17:47:12Z", 
              "releaseID": "01044-140631/001/XL", 
              "releaseTag": [
                "compiled"
              ], 
              "value": "2015-05-29"
            }
          ], 
          "rationale": [
            {
              "releaseDate": "2015-10-29T17:47:12Z", 
              "releaseID": "01044-140631/001/XL", 
              "releaseTag": [
                "compiled"
              ], 
              "value": "amendmentNumber: 000, awardDate: 2014-05-16, expiryDate: 2016-06-17, value: 16929.00 | amendmentNumber: 001, awardDate: 2015-05-29, expiryDate: 2016-06-17, value: 16929.00"
            }
          ]
        }, 
        "items": [
          {
            "classification": {
              "scheme": [
                {
                  "releaseDate": "2015-10-29T17:47:12Z", 
                  "releaseID": "01044-140631/001/XL", 
                  "releaseTag": [
                    "compiled"
                  ], 
                  "value": "GSIN"
                }
              ], 
              "id": [
                {
                  "releaseDate": "2015-10-29T17:47:12Z", 
                  "releaseID": "01044-140631/001/XL", 
                  "releaseTag": [
                    "compiled"
                  ], 
                  "value": "N7030"
                }
              ]
            }, 
            "id": "N7030", 
            "description_en": [
              {
                "releaseDate": "2015-10-29T17:47:12Z", 
                "releaseID": "01044-140631/001/XL", 
                "releaseTag": [
                  "compiled"
                ], 
                "value": "ADP Software"
              }
            ], 
            "description_fr": [
              {
                "releaseDate": "2015-10-29T17:47:12Z", 
                "releaseID": "01044-140631/001/XL", 
                "releaseTag": [
                  "compiled"
                ], 
                "value": "Logiciel TAI"
              }
            ]
          }
        ], 
        "title_en": [
          {
            "releaseDate": "2015-10-29T17:47:12Z", 
            "releaseID": "01044-140631/001/XL", 
            "releaseTag": [
              "compiled"
            ], 
            "value": "ADP Software"
          }
        ], 
        "period": {
          "startDate": [
            {
              "releaseDate": "2015-10-29T17:47:12Z", 
              "releaseID": "01044-140631/001/XL", 
              "releaseTag": [
                "compiled"
              ], 
              "value": "2014-05-16"
            }
          ], 
          "endDate": [
            {
              "releaseDate": "2015-10-29T17:47:12Z", 
              "releaseID": "01044-140631/001/XL", 
              "releaseTag": [
                "compiled"
              ], 
              "value": "2016-06-17"
            }
          ]
        }, 
        "value": {
          "currency": [
            {
              "releaseDate": "2015-10-29T17:47:12Z", 
              "releaseID": "01044-140631/001/XL", 
              "releaseTag": [
                "compiled"
              ], 
              "value": "CAD"
            }
          ], 
          "amount": [
            {
              "releaseDate": "2015-10-29T17:47:12Z", 
              "releaseID": "01044-140631/001/XL", 
              "releaseTag": [
                "compiled"
              ], 
              "value": 33858
            }
          ]
        }, 
        "title_fr": [
          {
            "releaseDate": "2015-10-29T17:47:12Z", 
            "releaseID": "01044-140631/001/XL", 
            "releaseTag": [
              "compiled"
            ], 
            "value": "Logiciel TAI"
          }
        ], 
        "awardID": [
          {
            "releaseDate": "2015-10-29T17:47:12Z", 
            "releaseID": "01044-140631/001/XL", 
            "releaseTag": [
              "compiled"
            ], 
            "value": "01044-140631/001/XL"
          }
        ], 
        "id": "01044-140631/001/XL"
      }
    ], 
    "ocid": "ocds-34a6hz-01044-140631/001/XL", 
    "packageInfo": {
      "publisher": {
        "documentation_en": [
          {
            "releaseDate": "2015-10-29T17:47:12Z", 
            "releaseID": "01044-140631/001/XL", 
            "releaseTag": [
              "compiled"
            ], 
            "value": "https://buyandsell.gc.ca/procurement-data/open-contracting-data-standard-pilot/download-ocds-pilot-data"
          }
        ], 
        "documentation_fr": [
          {
            "releaseDate": "2015-10-29T17:47:12Z", 
            "releaseID": "01044-140631/001/XL", 
            "releaseTag": [
              "compiled"
            ], 
            "value": "https://achatsetventes.gc.ca/donnees-sur-l-approvisionnement/projet-pilote-norme-relative-aux-donnees-sur-la-passation-de-marches-ouverts/telecharger-les-donnees-du-projet-pilote-ndpmo"
          }
        ], 
        "name": [
          {
            "releaseDate": "2015-10-29T17:47:12Z", 
            "releaseID": "01044-140631/001/XL", 
            "releaseTag": [
              "compiled"
            ], 
            "value": "Buyandsell.gc.ca - Achatsetventes.gc.ca"
          }
        ], 
        "uri_en": [
          {
            "releaseDate": "2015-10-29T17:47:12Z", 
            "releaseID": "01044-140631/001/XL", 
            "releaseTag": [
              "compiled"
            ], 
            "value": "https://buyandsell.gc.ca"
          }
        ], 
        "uri_fr": [
          {
            "releaseDate": "2015-10-29T17:47:12Z", 
            "releaseID": "01044-140631/001/XL", 
            "releaseTag": [
              "compiled"
            ], 
            "value": "https://achatsetventes.gc.ca"
          }
        ]
      }, 
      "uri": [
        {
          "releaseDate": "2015-10-29T17:47:12Z", 
          "releaseID": "01044-140631/001/XL", 
          "releaseTag": [
            "compiled"
          ], 
          "value": "https://buyandsell.gc.ca/cds/public/ocds/tpsgc-pwgsc_ocds_EF-FY-15-16.json"
        }
      ], 
      "publishedDate": [
        {
          "releaseDate": "2015-10-29T17:47:12Z", 
          "releaseID": "01044-140631/001/XL", 
          "releaseTag": [
            "compiled"
          ], 
          "value": "2015-11-18T21:59:18Z"
        }
      ]
    }, 
    "initiationType": [
      {
        "releaseDate": "2015-10-29T17:47:12Z", 
        "releaseID": "01044-140631/001/XL", 
        "releaseTag": [
          "compiled"
        ], 
        "value": "tender"
      }
    ], 
    "buyer": {
      "id": [
        {
          "releaseDate": "2015-10-29T17:47:12Z", 
          "releaseID": "01044-140631/001/XL", 
          "releaseTag": [
            "compiled"
          ], 
          "value": "MISC-BUYANDSELLGCCA-01"
        }
      ], 
      "name": [
        {
          "releaseDate": "2015-10-29T17:47:12Z", 
          "releaseID": "01044-140631/001/XL", 
          "releaseTag": [
            "compiled"
          ], 
          "value": ""
        }
      ]
    }, 
    "version": [
      {
        "releaseDate": "2015-10-29T17:47:12Z", 
        "releaseID": "01044-140631/001/XL", 
        "releaseTag": [
          "compiled"
        ], 
        "value": "1.1"
      }
    ], 
    "parties": [
      {
        "name_fr": [
          {
            "releaseDate": "2015-10-29T17:47:12Z", 
            "releaseID": "01044-140631/001/XL", 
            "releaseTag": [
              "compiled"
            ], 
            "value": "Agriculture et Agroalimentaire Canada"
          }
        ], 
        "roles": [
          [
            {
              "releaseDate": "2015-10-29T17:47:12Z", 
              "releaseID": "01044-140631/001/XL", 
              "releaseTag": [
                "compiled"
              ], 
              "value": "buyer"
            }
          ]
        ], 
        "address": {
          "countryName": [
            {
              "releaseDate": "2015-10-29T17:47:12Z", 
              "releaseID": "01044-140631/001/XL", 
              "releaseTag": [
                "compiled"
              ], 
              "value": "Canada"
            }
          ], 
          "postalCode": [
            {
              "releaseDate": "2015-10-29T17:47:12Z", 
              "releaseID": "01044-140631/001/XL", 
              "releaseTag": [
                "compiled"
              ], 
              "value": "K1A0C5"
            }
          ], 
          "region": [
            {
              "releaseDate": "2015-10-29T17:47:12Z", 
              "releaseID": "01044-140631/001/XL", 
              "releaseTag": [
                "compiled"
              ], 
              "value": "Ontario"
            }
          ], 
          "streetAddress": [
            {
              "releaseDate": "2015-10-29T17:47:12Z", 
              "releaseID": "01044-140631/001/XL", 
              "releaseTag": [
                "compiled"
              ], 
              "value": "PROCUREMENT DIV.5TH FL.TWR 3"
            }
          ], 
          "locality": [
            {
              "releaseDate": "2015-10-29T17:47:12Z", 
              "releaseID": "01044-140631/001/XL", 
              "releaseTag": [
                "compiled"
              ], 
              "value": "OTTAWA"
            }
          ]
        }, 
        "name_en": [
          {
            "releaseDate": "2015-10-29T17:47:12Z", 
            "releaseID": "01044-140631/001/XL", 
            "releaseTag": [
              "compiled"
            ], 
            "value": "Agriculture and Agri-Food Canada"
          }
        ], 
        "identifier": {
          "scheme": [
            {
              "releaseDate": "2015-10-29T17:47:12Z", 
              "releaseID": "01044-140631/001/XL", 
              "releaseTag": [
                "compiled"
              ], 
              "value": "MISC-BUYANDSELLGCCA"
            }
          ], 
          "legalName_en": [
            {
              "releaseDate": "2015-10-29T17:47:12Z", 
              "releaseID": "01044-140631/001/XL", 
              "releaseTag": [
                "compiled"
              ], 
              "value": "Agriculture and Agri-Food Canada"
            }
          ], 
          "id": [
            {
              "releaseDate": "2015-10-29T17:47:12Z", 
              "releaseID": "01044-140631/001/XL", 
              "releaseTag": [
                "compiled"
              ], 
              "value": "01"
            }
          ], 
          "legalName_fr": [
            {
              "releaseDate": "2015-10-29T17:47:12Z", 
              "releaseID": "01044-140631/001/XL", 
              "releaseTag": [
                "compiled"
              ], 
              "value": "Agriculture et Agroalimentaire Canada"
            }
          ]
        }, 
        "id": "MISC-BUYANDSELLGCCA-01"
      }
    ], 
    "validationErrors": [
      {
        "releaseDate": "2015-10-29T17:47:12Z", 
        "releaseID": "01044-140631/001/XL", 
        "releaseTag": [
          "compiled"
        ], 
        "value": "properties/buyer/properties/name/minLength: '' is too short"
      }
    ]
  }, 
  "releases": [
    {
      "version": "1.1", 
      "language": "en", 
      "contracts": [
        {
          "status": "active", 
          "amendment": {
            "date": "2015-05-29", 
            "rationale": "amendmentNumber: 000, awardDate: 2014-05-16, expiryDate: 2016-06-17, value: 16929.00 | amendmentNumber: 001, awardDate: 2015-05-29, expiryDate: 2016-06-17, value: 16929.00"
          }, 
          "items": [
            {
              "classification": {
                "scheme": "GSIN", 
                "id": "N7030"
              }, 
              "id": "N7030", 
              "description_en": "ADP Software", 
              "description_fr": "Logiciel TAI"
            }
          ], 
          "title_en": "ADP Software", 
          "period": {
            "startDate": "2014-05-16", 
            "endDate": "2016-06-17"
          }, 
          "value": {
            "currency": "CAD", 
            "amount": 33858
          }, 
          "title_fr": "Logiciel TAI", 
          "awardID": "01044-140631/001/XL", 
          "id": "01044-140631/001/XL"
        }
      ], 
      "ocid": "ocds-34a6hz-01044-140631/001/XL", 
      "packageInfo": {
        "publisher": {
          "documentation_en": "https://buyandsell.gc.ca/procurement-data/open-contracting-data-standard-pilot/download-ocds-pilot-data", 
          "documentation_fr": "https://achatsetventes.gc.ca/donnees-sur-l-approvisionnement/projet-pilote-norme-relative-aux-donnees-sur-la-passation-de-marches-ouverts/telecharger-les-donnees-du-projet-pilote-ndpmo", 
          "name": "Buyandsell.gc.ca - Achatsetventes.gc.ca", 
          "uri_en": "https://buyandsell.gc.ca", 
          "uri_fr": "https://achatsetventes.gc.ca"
        }, 
        "uri": "https://buyandsell.gc.ca/cds/public/ocds/tpsgc-pwgsc_ocds_EF-FY-15-16.json", 
        "publishedDate": "2015-11-18T21:59:18Z"
      }, 
      "initiationType": "tender", 
      "buyer": {
        "id": "MISC-BUYANDSELLGCCA-01", 
        "name": ""
      }, 
      "tag": [
        "compiled"
      ], 
      "parties": [
        {
          "name_fr": "Agriculture et Agroalimentaire Canada", 
          "roles": [
            "buyer"
          ], 
          "address": {
            "postalCode": "K1A0C5", 
            "countryName": "Canada", 
            "streetAddress": "PROCUREMENT DIV.5TH FL.TWR 3", 
            "region": "Ontario", 
            "locality": "OTTAWA"
          }, 
          "name_en": "Agriculture and Agri-Food Canada", 
          "identifier": {
            "scheme": "MISC-BUYANDSELLGCCA", 
            "legalName_en": "Agriculture and Agri-Food Canada", 
            "id": "01", 
            "legalName_fr": "Agriculture et Agroalimentaire Canada"
          }, 
          "id": "MISC-BUYANDSELLGCCA-01"
        }
      ], 
      "date": "2015-10-29T17:47:12Z", 
      "validationErrors": "properties/buyer/properties/name/minLength: '' is too short", 
      "id": "01044-140631/001/XL"
    }
  ], 
  "compiledRelease": {
    "version": "1.1", 
    "language": "en", 
    "buyer": {
      "id": "MISC-BUYANDSELLGCCA-01", 
      "name": ""
    }, 
    "ocid": "ocds-34a6hz-01044-140631/001/XL", 
    "contracts": [
      {
        "status": "active", 
        "amendment": {
          "date": "2015-05-29", 
          "rationale": "amendmentNumber: 000, awardDate: 2014-05-16, expiryDate: 2016-06-17, value: 16929.00 | amendmentNumber: 001, awardDate: 2015-05-29, expiryDate: 2016-06-17, value: 16929.00"
        }, 
        "items": [
          {
            "classification": {
              "scheme": "GSIN", 
              "id": "N7030"
            }, 
            "id": "N7030", 
            "description_en": "ADP Software", 
            "description_fr": "Logiciel TAI"
          }
        ], 
        "title_en": "ADP Software", 
        "period": {
          "startDate": "2014-05-16", 
          "endDate": "2016-06-17"
        }, 
        "value": {
          "currency": "CAD", 
          "amount": 33858
        }, 
        "title_fr": "Logiciel TAI", 
        "awardID": "01044-140631/001/XL", 
        "id": "01044-140631/001/XL"
      }
    ], 
    "packageInfo": {
      "publisher": {
        "documentation_en": "https://buyandsell.gc.ca/procurement-data/open-contracting-data-standard-pilot/download-ocds-pilot-data", 
        "documentation_fr": "https://achatsetventes.gc.ca/donnees-sur-l-approvisionnement/projet-pilote-norme-relative-aux-donnees-sur-la-passation-de-marches-ouverts/telecharger-les-donnees-du-projet-pilote-ndpmo", 
        "name": "Buyandsell.gc.ca - Achatsetventes.gc.ca", 
        "uri_en": "https://buyandsell.gc.ca", 
        "uri_fr": "https://achatsetventes.gc.ca"
      }, 
      "uri": "https://buyandsell.gc.ca/cds/public/ocds/tpsgc-pwgsc_ocds_EF-FY-15-16.json", 
      "publishedDate": "2015-11-18T21:59:18Z"
    }, 
    "initiationType": "tender", 
    "validationErrors": "properties/buyer/properties/name/minLength: '' is too short", 
    "tag": [
      "compiled"
    ], 
    "parties": [
      {
        "name_fr": "Agriculture et Agroalimentaire Canada", 
        "roles": [
          "buyer"
        ], 
        "address": {
          "countryName": "Canada", 
          "postalCode": "K1A0C5", 
          "region": "Ontario", 
          "streetAddress": "PROCUREMENT DIV.5TH FL.TWR 3", 
          "locality": "OTTAWA"
        }, 
        "name_en": "Agriculture and Agri-Food Canada", 
        "identifier": {
          "scheme": "MISC-BUYANDSELLGCCA", 
          "legalName_en": "Agriculture and Agri-Food Canada", 
          "id": "01", 
          "legalName_fr": "Agriculture et Agroalimentaire Canada"
        }, 
        "id": "MISC-BUYANDSELLGCCA-01"
      }
    ], 
    "date": "2015-10-29T17:47:12Z", 
    "id": "01044-140631/001/XL"
  }
}