{
  "compiledRelease": {
    "tag": [
      "compiled"
    ],
    "date": "2017-05-12T00:00:00.000Z",
    "id": "19295404",
    "initiationType": "tender",
    "language": "md",
    "ocid": "ocds-ngfbwp-19295404",
    "validationErrors": "properties/tender/properties/status/enum: 'Evaluarea ofertelor' is not one of ['planned', 'active', 'cancelled', 'unsuccessful', 'complete', None]",
    "version": "1.1",
    "buyer": {
      "id": "9904a1b6cc8dba742934f7df800b7827",
      "name": "DIREC\u0162IA \u00ceNV\u0102\u0162\u0102M\u00ceNT GENERAL CIMI\u015eLIA"
    },
    "packageInfo": {
      "publishedDate": "2016-11-07T00:00:00.00Z",
      "uri": "http://moldova-demo.yipl.com.np/ocds-api/year/2017",
      "publisher": {
        "name": "Public Procurement Agency",
        "scheme": null,
        "uid": null,
        "uri": "https://tender.gov.md"
      }
    },
    "tender": {
      "awardCriteria": "",
      "awardCriteriaDetails": "",
      "description": "",
      "eligibilityCriteria": "",
      "id": "19295404",
      "numberOfTenders": "",
      "procurementMethod": "Licita\u0163ie public\u0103",
      "procurementMethodRationale": "",
      "status": "Evaluarea ofertelor",
      "submissionMethodDetails": "",
      "tenderers": [
        {
          "id": "8d97cc040a6218bd4f90bf8d938b46ca",
          "name": ""
        }
      ],
      "title": "Tender Ref 17/01430 Bulletin 38",
      "amendment": {
        "changes": {}
      },
      "procuringEntity": {
        "id": "9904a1b6cc8dba742934f7df800b7827",
        "name": "DIREC\u0162IA \u00ceNV\u0102\u0162\u0102M\u00ceNT GENERAL CIMI\u015eLIA"
      },
      "submissionMethod": [
        "written"
      ],
      "tenderPeriod": {
        "endDate": "2017-06-02T10:00:00.000Z",
        "startDate": "2017-05-12T00:00:00.000Z"
      },
      "value": {
        "amount": "",
        "currency": ""
      },
      "documents": [
        {
          "id": "",
          "datePublished": "",
          "format": "",
          "title": "",
          "url": ""
        }
      ],
      "milestones": [
        {
          "id": 0,
          "documents": {}
        }
      ]
    },
    "parties": [
      {
        "id": "9904a1b6cc8dba742934f7df800b7827",
        "name": "DIREC\u0162IA \u00ceNV\u0102\u0162\u0102M\u00ceNT GENERAL CIMI\u015eLIA",
        "roles": [
          "buyer",
          "procuringEntity"
        ]
      },
      {
        "id": "8d97cc040a6218bd4f90bf8d938b46ca",
        "name": "",
        "roles": [
          "tenderer"
        ]
      }
    ]
  },
  "versionedRelease": {
    "ocid": "ocds-ngfbwp-19295404",
    "initiationType": [
      {
        "releaseID": "19295404",
        "releaseDate": "2017-05-12T00:00:00.000Z",
        "releaseTag": [
          "tender",
          "award",
          "contract"
        ],
        "value": "tender"
      }
    ],
    "language": [
      {
        "releaseID": "19295404",
        "releaseDate": "2017-05-12T00:00:00.000Z",
        "releaseTag": [
          "tender",
          "award",
          "contract"
        ],
        "value": "md"
      }
    ],
    "validationErrors": [
      {
        "releaseID": "19295404",
        "releaseDate": "2017-05-12T00:00:00.000Z",
        "releaseTag": [
          "tender",
          "award",
          "contract"
        ],
        "value": "properties/tender/properties/status/enum: 'Evaluarea ofertelor' is not one of ['planned', 'active', 'cancelled', 'unsuccessful', 'complete', None]"
      }
    ],
    "version": [
      {
        "releaseID": "19295404",
        "releaseDate": "2017-05-12T00:00:00.000Z",
        "releaseTag": [
          "tender",
          "award",
          "contract"
        ],
        "value": "1.1"
      }
    ],
    "buyer": {
      "id": [
        {
          "releaseID": "19295404",
          "releaseDate": "2017-05-12T00:00:00.000Z",
          "releaseTag": [
            "tender",
            "award",
            "contract"
          ],
          "value": "9904a1b6cc8dba742934f7df800b7827"
        }
      ],
      "name": [
        {
          "releaseID": "19295404",
          "releaseDate": "2017-05-12T00:00:00.000Z",
          "releaseTag": [
            "tender",
            "award",
            "contract"
          ],
          "value": "DIREC\u0162IA \u00ceNV\u0102\u0162\u0102M\u00ceNT GENERAL CIMI\u015eLIA"
        }
      ]
    },
    "packageInfo": {
      "publishedDate": [
        {
          "releaseID": "19295404",
          "releaseDate": "2017-05-12T00:00:00.000Z",
          "releaseTag": [
            "tender",
            "award",
            "contract"
          ],
          "value": "2016-11-07T00:00:00.00Z"
        }
      ],
      "uri": [
        {
          "releaseID": "19295404",
          "releaseDate": "2017-05-12T00:00:00.000Z",
          "releaseTag": [
            "tender",
            "award",
            "contract"
          ],
          "value": "http://moldova-demo.yipl.com.np/ocds-api/year/2017"
        }
      ],
      "publisher": {
        "name": [
          {
            "releaseID": "19295404",
            "releaseDate": "2017-05-12T00:00:00.000Z",
            "releaseTag": [
              "tender",
              "award",
              "contract"
            ],
            "value": "Public Procurement Agency"
          }
        ],
        "scheme": [
          {
            "releaseID": "19295404",
            "releaseDate": "2017-05-12T00:00:00.000Z",
            "releaseTag": [
              "tender",
              "award",
              "contract"
            ],
            "value": null
          }
        ],
        "uid": [
          {
            "releaseID": "19295404",
            "releaseDate": "2017-05-12T00:00:00.000Z",
            "releaseTag": [
              "tender",
              "award",
              "contract"
            ],
            "value": null
          }
        ],
        "uri": [
          {
            "releaseID": "19295404",
            "releaseDate": "2017-05-12T00:00:00.000Z",
            "releaseTag": [
              "tender",
              "award",
              "contract"
            ],
            "value": "https://tender.gov.md"
          }
        ]
      }
    },
    "tender": {
      "awardCriteria": [
        {
          "releaseID": "19295404",
          "releaseDate": "2017-05-12T00:00:00.000Z",
          "releaseTag": [
            "tender",
            "award",
            "contract"
          ],
          "value": ""
        }
      ],
      "awardCriteriaDetails": [
        {
          "releaseID": "19295404",
          "releaseDate": "2017-05-12T00:00:00.000Z",
          "releaseTag": [
            "tender",
            "award",
            "contract"
          ],
          "value": ""
        }
      ],
      "description": [
        {
          "releaseID": "19295404",
          "releaseDate": "2017-05-12T00:00:00.000Z",
          "releaseTag": [
            "tender",
            "award",
            "contract"
          ],
          "value": ""
        }
      ],
      "eligibilityCriteria": [
        {
          "releaseID": "19295404",
          "releaseDate": "2017-05-12T00:00:00.000Z",
          "releaseTag": [
            "tender",
            "award",
            "contract"
          ],
          "value": ""
        }
      ],
      "id": [
        {
          "releaseID": "19295404",
          "releaseDate": "2017-05-12T00:00:00.000Z",
          "releaseTag": [
            "tender",
            "award",
            "contract"
          ],
          "value": "19295404"
        }
      ],
      "numberOfTenders": [
        {
          "releaseID": "19295404",
          "releaseDate": "2017-05-12T00:00:00.000Z",
          "releaseTag": [
            "tender",
            "award",
            "contract"
          ],
          "value": ""
        }
      ],
      "procurementMethod": [
        {
          "releaseID": "19295404",
          "releaseDate": "2017-05-12T00:00:00.000Z",
          "releaseTag": [
            "tender",
            "award",
            "contract"
          ],
          "value": "Licita\u0163ie public\u0103"
        }
      ],
      "procurementMethodRationale": [
        {
          "releaseID": "19295404",
          "releaseDate": "2017-05-12T00:00:00.000Z",
          "releaseTag": [
            "tender",
            "award",
            "contract"
          ],
          "value": ""
        }
      ],
      "status": [
        {
          "releaseID": "19295404",
          "releaseDate": "2017-05-12T00:00:00.000Z",
          "releaseTag": [
            "tender",
            "award",
            "contract"
          ],
          "value": "Evaluarea ofertelor"
        }
      ],
      "submissionMethodDetails": [
        {
          "releaseID": "19295404",
          "releaseDate": "2017-05-12T00:00:00.000Z",
          "releaseTag": [
            "tender",
            "award",
            "contract"
          ],
          "value": ""
        }
      ],
      "tenderers": [
        {
          "releaseID": "19295404",
          "releaseDate": "2017-05-12T00:00:00.000Z",
          "releaseTag": [
            "tender",
            "award",
            "contract"
          ],
          "value": [
            {
              "id": "8d97cc040a6218bd4f90bf8d938b46ca",
              "name": ""
            }
          ]
        }
      ],
      "title": [
        {
          "releaseID": "19295404",
          "releaseDate": "2017-05-12T00:00:00.000Z",
          "releaseTag": [
            "tender",
            "award",
            "contract"
          ],
          "value": "Tender Ref 17/01430 Bulletin 38"
        }
      ],
      "amendment": {
        "changes": [
          {
            "releaseID": "19295404",
            "releaseDate": "2017-05-12T00:00:00.000Z",
            "releaseTag": [
              "tender",
              "award",
              "contract"
            ],
            "value": {}
          }
        ]
      },
      "procuringEntity": {
        "id": [
          {
            "releaseID": "19295404",
            "releaseDate": "2017-05-12T00:00:00.000Z",
            "releaseTag": [
              "tender",
              "award",
              "contract"
            ],
            "value": "9904a1b6cc8dba742934f7df800b7827"
          }
        ],
        "name": [
          {
            "releaseID": "19295404",
            "releaseDate": "2017-05-12T00:00:00.000Z",
            "releaseTag": [
              "tender",
              "award",
              "contract"
            ],
            "value": "DIREC\u0162IA \u00ceNV\u0102\u0162\u0102M\u00ceNT GENERAL CIMI\u015eLIA"
          }
        ]
      },
      "submissionMethod": [
        [
          {
            "releaseID": "19295404",
            "releaseDate": "2017-05-12T00:00:00.000Z",
            "releaseTag": [
              "tender",
              "award",
              "contract"
            ],
            "value": "written"
          }
        ]
      ],
      "tenderPeriod": {
        "endDate": [
          {
            "releaseID": "19295404",
            "releaseDate": "2017-05-12T00:00:00.000Z",
            "releaseTag": [
              "tender",
              "award",
              "contract"
            ],
            "value": "2017-06-02T10:00:00.000Z"
          }
        ],
        "startDate": [
          {
            "releaseID": "19295404",
            "releaseDate": "2017-05-12T00:00:00.000Z",
            "releaseTag": [
              "tender",
              "award",
              "contract"
            ],
            "value": "2017-05-12T00:00:00.000Z"
          }
        ]
      },
      "value": {
        "amount": [
          {
            "releaseID": "19295404",
            "releaseDate": "2017-05-12T00:00:00.000Z",
            "releaseTag": [
              "tender",
              "award",
              "contract"
            ],
            "value": ""
          }
        ],
        "currency": [
          {
            "releaseID": "19295404",
            "releaseDate": "2017-05-12T00:00:00.000Z",
            "releaseTag": [
              "tender",
              "award",
              "contract"
            ],
            "value": ""
          }
        ]
      },
      "documents": [
        {
          "id": "",
          "datePublished": [
            {
              "releaseID": "19295404",
              "releaseDate": "2017-05-12T00:00:00.000Z",
              "releaseTag": [
                "tender",
                "award",
                "contract"
              ],
              "value": ""
            }
          ],
          "format": [
            {
              "releaseID": "19295404",
              "releaseDate": "2017-05-12T00:00:00.000Z",
              "releaseTag": [
                "tender",
                "award",
                "contract"
              ],
              "value": ""
            }
          ],
          "title": [
            {
              "releaseID": "19295404",
              "releaseDate": "2017-05-12T00:00:00.000Z",
              "releaseTag": [
                "tender",
                "award",
                "contract"
              ],
              "value": ""
            }
          ],
          "url": [
            {
              "releaseID": "19295404",
              "releaseDate": "2017-05-12T00:00:00.000Z",
              "releaseTag": [
                "tender",
                "award",
                "contract"
              ],
              "value": ""
            }
          ]
        }
      ],
      "milestones": [
        {
          "id": 0,
          "documents": [
            {
              "releaseID": "19295404",
              "releaseDate": "2017-05-12T00:00:00.000Z",
              "releaseTag": [
                "tender",
                "award",
                "contract"
              ],
              "value": {}
            }
          ]
        }
      ]
    },
    "parties": [
      {
        "id": "9904a1b6cc8dba742934f7df800b7827",
        "name": [
          {
            "releaseID": "19295404",
            "releaseDate": "2017-05-12T00:00:00.000Z",
            "releaseTag": [
              "tender",
              "award",
              "contract"
            ],
            "value": "DIREC\u0162IA \u00ceNV\u0102\u0162\u0102M\u00ceNT GENERAL CIMI\u015eLIA"
          }
        ],
        "roles": [
          [
            {
              "releaseID": "19295404",
              "releaseDate": "2017-05-12T00:00:00.000Z",
              "releaseTag": [
                "tender",
                "award",
                "contract"
              ],
              "value": "buyer"
            }
          ],
          [
            {
              "releaseID": "19295404",
              "releaseDate": "2017-05-12T00:00:00.000Z",
              "releaseTag": [
                "tender",
                "award",
                "contract"
              ],
              "value": "procuringEntity"
            }
          ]
        ]
      },
      {
        "id": "8d97cc040a6218bd4f90bf8d938b46ca",
        "name": [
          {
            "releaseID": "19295404",
            "releaseDate": "2017-05-12T00:00:00.000Z",
            "releaseTag": [
              "tender",
              "award",
              "contract"
            ],
            "value": ""
          }
        ],
        "roles": [
          [
            {
              "releaseID": "19295404",
              "releaseDate": "2017-05-12T00:00:00.000Z",
              "releaseTag": [
                "tender",
                "award",
                "contract"
              ],
              "value": "tenderer"
            }
          ]
        ]
      }
    ]
  },
  "releases": [
    {
      "ocid": "ocds-ngfbwp-19295404",
      "id": "19295404",
      "date": "2017-05-12T00:00:00.000Z",
      "language": "md",
      "tag": [
        "tender",
        "award",
        "contract"
      ],
      "initiationType": "tender",
      "parties": [
        {
          "id": "9904a1b6cc8dba742934f7df800b7827",
          "name": "DIREC\u0162IA \u00ceNV\u0102\u0162\u0102M\u00ceNT GENERAL CIMI\u015eLIA",
          "roles": [
            "buyer",
            "procuringEntity"
          ]
        },
        {
          "id": "8d97cc040a6218bd4f90bf8d938b46ca",
          "name": "",
          "roles": [
            "tenderer"
          ]
        }
      ],
      "tender": {
        "id": "19295404",
        "title": "Tender Ref 17/01430 Bulletin 38",
        "description": "",
        "status": "Evaluarea ofertelor",
        "value": {
          "amount": "",
          "currency": ""
        },
        "procurementMethod": "Licita\u0163ie public\u0103",
        "procurementMethodRationale": "",
        "awardCriteria": "",
        "awardCriteriaDetails": "",
        "submissionMethod": [
          "written"
        ],
        "submissionMethodDetails": "",
        "tenderPeriod": {
          "startDate": "2017-05-12T00:00:00.000Z",
          "endDate": "2017-06-02T10:00:00.000Z"
        },
        "eligibilityCriteria": "",
        "numberOfTenders": "",
        "tenderers": [
          {
            "id": "8d97cc040a6218bd4f90bf8d938b46ca",
            "name": ""
          }
        ],
        "procuringEntity": {
          "id": "9904a1b6cc8dba742934f7df800b7827",
          "name": "DIREC\u0162IA \u00ceNV\u0102\u0162\u0102M\u00ceNT GENERAL CIMI\u015eLIA"
        },
        "documents": [
          {
            "id": "",
            "title": "",
            "url": "",
            "datePublished": "",
            "format": ""
          }
        ],
        "milestones": [
          {
            "documents": {}
          }
        ],
        "amendment": {
          "changes": {}
        }
      },
      "buyer": {
        "id": "9904a1b6cc8dba742934f7df800b7827",
        "name": "DIREC\u0162IA \u00ceNV\u0102\u0162\u0102M\u00ceNT GENERAL CIMI\u015eLIA"
      },
      "packageInfo": {
        "uri": "http://moldova-demo.yipl.com.np/ocds-api/year/2017",
        "publishedDate": "2016-11-07T00:00:00.00Z",
        "publisher": {
          "scheme": null,
          "name": "Public Procurement Agency",
          "uri": "https://tender.gov.md",
          "uid": null
        }
      },
      "version": "1.1",
      "validationErrors": "properties/tender/properties/status/enum: 'Evaluarea ofertelor' is not one of ['planned', 'active', 'cancelled', 'unsuccessful', 'complete', None]"
    }
  ],
  "publisher": {
    "scheme": null,
    "name": "Public Procurement Agency",
    "uri": "https://tender.gov.md",
    "uid": null
  }
}