{
  "tag": [
    "compiled"
  ],
  "initiationType": "tender",
  "id": "274744-adquisicion-materiales-mantenimiento-red-planta-externa-ad-referendum-1",
  "awards": [
    {
      "date": "2016-07-14T17:40:06-04:00",
      "id": "274744-adquisicion-materiales-mantenimiento-red-planta-externa-ad-referendum-1",
      "value": {
        "amount": 771657000.0,
        "currency": "PYG"
      },
      "url": "https://www.contrataciones.gov.py/datos/id/adjudicaciones/274744-adquisicion-materiales-mantenimiento-red-planta-externa-ad-referendum-1",
      "suppliers": [
        {
          "address": {
            "countryName": "Paraguay",
            "region": "Central",
            "streetAddress": "JUAN MAX BOETTNER 930",
            "locality": "ASUNCION (DISTRITO)",
            "postalCode": ""
          },
          "contactPoint": {
            "telephone": "611230",
            "url": null,
            "faxNumber": "",
            "email": "gustaqui@pla.net.py",
            "name": "GUSTAVO ALBERTO AQUINO ALFIERI"
          },
          "identifier": {
            "id": "368894-1",
            "legalName": "GUSTAVO ALBERTO AQUINO ALFIERI",
            "scheme": "Registro Único de Contribuyente emitido por el Ministerio de Hacienda del Gobierno de Paraguay"
          },
          "name": "GUSTAVO ALBERTO AQUINO ALFIERI"
        },
        {
          "address": {
            "countryName": "Paraguay",
            "region": "Asunción",
            "streetAddress": "INGLATERRA N° 143 C/ ARTIGAS.",
            "locality": "ASUNCIÓN.",
            "postalCode": ""
          },
          "contactPoint": {
            "telephone": "021 295 748/9",
            "url": null,
            "faxNumber": "",
            "email": "lida.cuevas@pmc.com.py",
            "name": "NELSON FRANCISCO VERA QUINTANA."
          },
          "identifier": {
            "id": "855506-0",
            "legalName": "NELSON FRANCISCO VERA QUINTANA",
            "scheme": "Registro Único de Contribuyente emitido por el Ministerio de Hacienda del Gobierno de Paraguay"
          },
          "name": "NELSON FRANCISCO VERA QUINTANA"
        }
      ],
      "status": "active",
      "title": "ADQUISICIÓN DE MATERIALES PARA MANTENIMIENTO DE LA RED DE PLANTA EXTERNA AD REFERENDUM"
    }
  ],
  "ocid": "ocds-03ad3f-274744",
  "planning": {
    "url": "https://www.contrataciones.gov.py/datos/id/planificaciones/274744-adquisicion-materiales-mantenimiento-red-planta-externa",
    "budget": {
      "amount": {
        "amount": 1000000000.0,
        "currency": "PYG"
      },
      "description": "ADQUISICIÓN DE MATERIALES PARA MANTENIMIENTO DE LA RED DE PLANTA EXTERNA"
    }
  },
  "date": "2017-10-10T10:47:04-04:00",
  "language": "es",
  "contracts": [
    {
      "url": "https://www.contrataciones.gov.py/datos/id/contratos/274744-gustavo-alberto-aquino-alfieri-3",
      "dateSigned": "2016-05-26T12:00:00-04:00",
      "documents": [
        {
          "id": "5nVp4twr1OI%3D",
          "url": "https://www.contrataciones.gov.py/documentos/download/adjudicacion/5nVp4twr1OI%253D",
          "format": "application/pdf",
          "language": "es",
          "documentType": "Acta de Apertura",
          "title": "Acta de Apertura"
        },
        {
          "id": "SNqBkMQdlPo%3D",
          "url": "https://www.contrataciones.gov.py/documentos/download/adjudicacion/SNqBkMQdlPo%253D",
          "format": "application/pdf",
          "language": "es",
          "documentType": "Cuadro Comparativo de Ofertas",
          "title": "Cuadro Comparativo de Ofertas"
        },
        {
          "id": "p07gLixAo2U%3D",
          "url": "https://www.contrataciones.gov.py/documentos/download/adjudicacion/p07gLixAo2U%253D",
          "format": "application/pdf",
          "language": "es",
          "documentType": "evaluationReports",
          "title": "Informe de Evaluación"
        },
        {
          "id": "ma2bkpn3keI%3D",
          "url": "https://www.contrataciones.gov.py/documentos/download/adjudicacion/ma2bkpn3keI%253D",
          "format": "application/pdf",
          "language": "es",
          "documentType": "evaluationReports",
          "title": "Informe de Evaluación"
        },
        {
          "id": "iXloWlrOxuQ%3D",
          "url": "https://www.contrataciones.gov.py/documentos/download/adjudicacion/iXloWlrOxuQ%253D",
          "format": "application/pdf",
          "language": "es",
          "documentType": "Notificación al Oferente",
          "title": "Notificación al Oferente"
        },
        {
          "id": "ZemDiFuxozc%3D",
          "url": "https://www.contrataciones.gov.py/documentos/download/adjudicacion/ZemDiFuxozc%253D",
          "format": "application/pdf",
          "language": "es",
          "documentType": "Orden de Compra o Contrato",
          "title": "Orden de Compra o Contrato"
        },
        {
          "id": "S69AX5nt3zo%3D",
          "url": "https://www.contrataciones.gov.py/documentos/download/adjudicacion/S69AX5nt3zo%253D",
          "format": "application/pdf",
          "language": "es",
          "documentType": "awardNotice",
          "title": "Resolución de Adjudicación"
        }
      ],
      "suppliers": {
        "identifiers": {
          "key": "274744-gustavo-alberto-aquino-alfieri-3"
        },
        "identifier": {
          "id": "368894-1",
          "legalName": "GUSTAVO ALBERTO AQUINO ALFIERI",
          "scheme": "Registro Único de Contribuyente emitido por el Ministerio de Hacienda del Gobierno de Paraguay"
        },
        "name": "GUSTAVO ALBERTO AQUINO ALFIERI"
      },
      "period": {
        "endDate": "2017-04-26T12:00:00-04:00",
        "startDate": "2016-05-26T12:00:00-04:00"
      },
      "dncpContractCode": "LP-40001-16-123961",
      "title": "ADQUISICIÓN DE MATERIALES PARA MANTENIMIENTO DE LA RED DE PLANTA EXTERNA AD REFERENDUM",
      "id": "274744-gustavo-alberto-aquino-alfieri-3",
      "value": {
        "amount": 548825024.0,
        "currency": "PYG"
      },
      "items": [
        {
          "unit": {
            "value": {
              "amount": 231.0,
              "currency": "PYG"
            },
            "name": "Unidad"
          },
          "id": "3xzWw1AEDSM%3D",
          "description": "Conector para cables multipares",
          "classification": {
            "schema": "Catálogo de productos, bienes y servicios de la Dirección Nacional de Contrataciones Públicas del Paraguay",
            "uri": "https://www.contrataciones.gov.py/datos/api/v2/doc/catalogo/nivel-5/39121409-014",
            "description": "Catálogo de productos, bienes y servicios de la Dirección Nacional de Contrataciones Públicas del Paraguay Nivel 5, basado en UNSPSC",
            "id": "39121409-014"
          },
          "quantity": 1000000.0
        },
        {
          "unit": {
            "value": {
              "amount": 146500.0,
              "currency": "PYG"
            },
            "name": "Unidad"
          },
          "id": "GycBT9vlkSs%3D",
          "description": "Manguito",
          "classification": {
            "schema": "Catálogo de productos, bienes y servicios de la Dirección Nacional de Contrataciones Públicas del Paraguay",
            "uri": "https://www.contrataciones.gov.py/datos/api/v2/doc/catalogo/nivel-5/43222825-001",
            "description": "Catálogo de productos, bienes y servicios de la Dirección Nacional de Contrataciones Públicas del Paraguay Nivel 5, basado en UNSPSC",
            "id": "43222825-001"
          },
          "quantity": 150.0
        },
        {
          "unit": {
            "value": {
              "amount": 165500.0,
              "currency": "PYG"
            },
            "name": "Unidad"
          },
          "id": "%2Buq8jkokrXg%3D",
          "description": "Manguito",
          "classification": {
            "schema": "Catálogo de productos, bienes y servicios de la Dirección Nacional de Contrataciones Públicas del Paraguay",
            "uri": "https://www.contrataciones.gov.py/datos/api/v2/doc/catalogo/nivel-5/43222825-001",
            "description": "Catálogo de productos, bienes y servicios de la Dirección Nacional de Contrataciones Públicas del Paraguay Nivel 5, basado en UNSPSC",
            "id": "43222825-001"
          },
          "quantity": 150.0
        },
        {
          "unit": {
            "value": {
              "amount": 722500.0,
              "currency": "PYG"
            },
            "name": "Unidad"
          },
          "id": "L%2Bbz8acj7yA%3D",
          "description": "Manguito",
          "classification": {
            "schema": "Catálogo de productos, bienes y servicios de la Dirección Nacional de Contrataciones Públicas del Paraguay",
            "uri": "https://www.contrataciones.gov.py/datos/api/v2/doc/catalogo/nivel-5/43222825-001",
            "description": "Catálogo de productos, bienes y servicios de la Dirección Nacional de Contrataciones Públicas del Paraguay Nivel 5, basado en UNSPSC",
            "id": "43222825-001"
          },
          "quantity": 100.0
        },
        {
          "unit": {
            "value": {
              "amount": 929000.0,
              "currency": "PYG"
            },
            "name": "Unidad"
          },
          "id": "KlDPdj6lQbY%3D",
          "description": "Manguito",
          "classification": {
            "schema": "Catálogo de productos, bienes y servicios de la Dirección Nacional de Contrataciones Públicas del Paraguay",
            "uri": "https://www.contrataciones.gov.py/datos/api/v2/doc/catalogo/nivel-5/43222825-001",
            "description": "Catálogo de productos, bienes y servicios de la Dirección Nacional de Contrataciones Públicas del Paraguay Nivel 5, basado en UNSPSC",
            "id": "43222825-001"
          },
          "quantity": 50.0
        },
        {
          "unit": {
            "value": {
              "amount": 1042500.0,
              "currency": "PYG"
            },
            "name": "Unidad"
          },
          "id": "xyQX4Ef5njo%3D",
          "description": "Manguito",
          "classification": {
            "schema": "Catálogo de productos, bienes y servicios de la Dirección Nacional de Contrataciones Públicas del Paraguay",
            "uri": "https://www.contrataciones.gov.py/datos/api/v2/doc/catalogo/nivel-5/43222825-001",
            "description": "Catálogo de productos, bienes y servicios de la Dirección Nacional de Contrataciones Públicas del Paraguay Nivel 5, basado en UNSPSC",
            "id": "43222825-001"
          },
          "quantity": 50.0
        },
        {
          "unit": {
            "value": {
              "amount": 475000.0,
              "currency": "PYG"
            },
            "name": "Unidad"
          },
          "id": "2HFFCf%2B122A%3D",
          "description": "Caja de conexion para modulos LSA ",
          "classification": {
            "schema": "Catálogo de productos, bienes y servicios de la Dirección Nacional de Contrataciones Públicas del Paraguay",
            "uri": "https://www.contrataciones.gov.py/datos/api/v2/doc/catalogo/nivel-5/43211601-008",
            "description": "Catálogo de productos, bienes y servicios de la Dirección Nacional de Contrataciones Públicas del Paraguay Nivel 5, basado en UNSPSC",
            "id": "43211601-008"
          },
          "quantity": 100.0
        },
        {
          "unit": {
            "value": {
              "amount": 419000.0,
              "currency": "PYG"
            },
            "name": "Unidad"
          },
          "id": "A5PvTlytSnA%3D",
          "description": "Caja de conexion para modulos LSA ",
          "classification": {
            "schema": "Catálogo de productos, bienes y servicios de la Dirección Nacional de Contrataciones Públicas del Paraguay",
            "uri": "https://www.contrataciones.gov.py/datos/api/v2/doc/catalogo/nivel-5/43211601-008",
            "description": "Catálogo de productos, bienes y servicios de la Dirección Nacional de Contrataciones Públicas del Paraguay Nivel 5, basado en UNSPSC",
            "id": "43211601-008"
          },
          "quantity": 100.0
        },
        {
          "unit": {
            "value": {
              "amount": 54000.0,
              "currency": "PYG"
            },
            "name": "Unidad"
          },
          "id": "wi3caj6Jbw0%3D",
          "description": "Conector para cables multipares",
          "classification": {
            "schema": "Catálogo de productos, bienes y servicios de la Dirección Nacional de Contrataciones Públicas del Paraguay",
            "uri": "https://www.contrataciones.gov.py/datos/api/v2/doc/catalogo/nivel-5/39121409-014",
            "description": "Catálogo de productos, bienes y servicios de la Dirección Nacional de Contrataciones Públicas del Paraguay Nivel 5, basado en UNSPSC",
            "id": "39121409-014"
          },
          "quantity": 100.0
        },
        {
          "unit": {
            "value": {
              "amount": 54000.0,
              "currency": "PYG"
            },
            "name": "Unidad"
          },
          "id": "O4yFAAtK5Cs%3D",
          "description": "Conector para cables multipares",
          "classification": {
            "schema": "Catálogo de productos, bienes y servicios de la Dirección Nacional de Contrataciones Públicas del Paraguay",
            "uri": "https://www.contrataciones.gov.py/datos/api/v2/doc/catalogo/nivel-5/39121409-014",
            "description": "Catálogo de productos, bienes y servicios de la Dirección Nacional de Contrataciones Públicas del Paraguay Nivel 5, basado en UNSPSC",
            "id": "39121409-014"
          },
          "quantity": 100.0
        }
      ],
      "lots": [
        {
          "id": "nYZlDIKXpLc%3D",
          "items": [
            "3xzWw1AEDSM%3D",
            "GycBT9vlkSs%3D",
            "%2Buq8jkokrXg%3D",
            "L%2Bbz8acj7yA%3D",
            "KlDPdj6lQbY%3D",
            "xyQX4Ef5njo%3D",
            "2HFFCf%2B122A%3D",
            "A5PvTlytSnA%3D",
            "wi3caj6Jbw0%3D",
            "O4yFAAtK5Cs%3D"
          ],
          "title": "Lote 1"
        }
      ],
      "status": "active",
      "awardID": "274744-adquisicion-materiales-mantenimiento-red-planta-externa-ad-referendum-1"
    },
    {
      "url": "https://www.contrataciones.gov.py/datos/id/contratos/274744-nelson-francisco-vera-quintana-2",
      "dateSigned": "2016-05-26T12:00:00-04:00",
      "documents": [
        {
          "id": "5nVp4twr1OI%3D",
          "url": "https://www.contrataciones.gov.py/documentos/download/adjudicacion/5nVp4twr1OI%253D",
          "format": "application/pdf",
          "language": "es",
          "documentType": "Acta de Apertura",
          "title": "Acta de Apertura"
        },
        {
          "id": "SNqBkMQdlPo%3D",
          "url": "https://www.contrataciones.gov.py/documentos/download/adjudicacion/SNqBkMQdlPo%253D",
          "format": "application/pdf",
          "language": "es",
          "documentType": "Cuadro Comparativo de Ofertas",
          "title": "Cuadro Comparativo de Ofertas"
        },
        {
          "id": "p07gLixAo2U%3D",
          "url": "https://www.contrataciones.gov.py/documentos/download/adjudicacion/p07gLixAo2U%253D",
          "format": "application/pdf",
          "language": "es",
          "documentType": "evaluationReports",
          "title": "Informe de Evaluación"
        },
        {
          "id": "ma2bkpn3keI%3D",
          "url": "https://www.contrataciones.gov.py/documentos/download/adjudicacion/ma2bkpn3keI%253D",
          "format": "application/pdf",
          "language": "es",
          "documentType": "evaluationReports",
          "title": "Informe de Evaluación"
        },
        {
          "id": "iXloWlrOxuQ%3D",
          "url": "https://www.contrataciones.gov.py/documentos/download/adjudicacion/iXloWlrOxuQ%253D",
          "format": "application/pdf",
          "language": "es",
          "documentType": "Notificación al Oferente",
          "title": "Notificación al Oferente"
        },
        {
          "id": "95wH3N9KvdE%3D",
          "url": "https://www.contrataciones.gov.py/documentos/download/adjudicacion/95wH3N9KvdE%253D",
          "format": "application/pdf",
          "language": "es",
          "documentType": "Orden de Compra o Contrato",
          "title": "Orden de Compra o Contrato"
        },
        {
          "id": "S69AX5nt3zo%3D",
          "url": "https://www.contrataciones.gov.py/documentos/download/adjudicacion/S69AX5nt3zo%253D",
          "format": "application/pdf",
          "language": "es",
          "documentType": "awardNotice",
          "title": "Resolución de Adjudicación"
        }
      ],
      "suppliers": {
        "identifiers": {
          "key": "274744-nelson-francisco-vera-quintana-2"
        },
        "identifier": {
          "id": "855506-0",
          "legalName": "NELSON FRANCISCO VERA QUINTANA",
          "scheme": "Registro Único de Contribuyente emitido por el Ministerio de Hacienda del Gobierno de Paraguay"
        },
        "name": "NELSON FRANCISCO VERA QUINTANA"
      },
      "period": {
        "endDate": "2017-04-26T12:00:00-04:00",
        "startDate": "2016-05-26T12:00:00-04:00"
      },
      "dncpContractCode": "LP-40001-16-123962",
      "title": "ADQUISICIÓN DE MATERIALES PARA MANTENIMIENTO DE LA RED DE PLANTA EXTERNA AD REFERENDUM",
      "id": "274744-nelson-francisco-vera-quintana-2",
      "value": {
        "amount": 222832000.0,
        "currency": "PYG"
      },
      "items": [
        {
          "unit": {
            "value": {
              "amount": 181100.0,
              "currency": "PYG"
            },
            "name": "Unidad"
          },
          "id": "yWlMMjl%2Ft9U%3D",
          "description": "Caja terminal",
          "classification": {
            "schema": "Catálogo de productos, bienes y servicios de la Dirección Nacional de Contrataciones Públicas del Paraguay",
            "uri": "https://www.contrataciones.gov.py/datos/api/v2/doc/catalogo/nivel-5/43222825-002",
            "description": "Catálogo de productos, bienes y servicios de la Dirección Nacional de Contrataciones Públicas del Paraguay Nivel 5, basado en UNSPSC",
            "id": "43222825-002"
          },
          "quantity": 200.0
        },
        {
          "unit": {
            "value": {
              "amount": 152450.0,
              "currency": "PYG"
            },
            "name": "Unidad"
          },
          "id": "eBWjiICSWz0%3D",
          "description": "Caja terminal",
          "classification": {
            "schema": "Catálogo de productos, bienes y servicios de la Dirección Nacional de Contrataciones Públicas del Paraguay",
            "uri": "https://www.contrataciones.gov.py/datos/api/v2/doc/catalogo/nivel-5/43222825-002",
            "description": "Catálogo de productos, bienes y servicios de la Dirección Nacional de Contrataciones Públicas del Paraguay Nivel 5, basado en UNSPSC",
            "id": "43222825-002"
          },
          "quantity": 400.0
        },
        {
          "unit": {
            "value": {
              "amount": 165700.0,
              "currency": "PYG"
            },
            "name": "Unidad"
          },
          "id": "1eZiY1phyuE%3D",
          "description": "Manguito",
          "classification": {
            "schema": "Catálogo de productos, bienes y servicios de la Dirección Nacional de Contrataciones Públicas del Paraguay",
            "uri": "https://www.contrataciones.gov.py/datos/api/v2/doc/catalogo/nivel-5/43222825-001",
            "description": "Catálogo de productos, bienes y servicios de la Dirección Nacional de Contrataciones Públicas del Paraguay Nivel 5, basado en UNSPSC",
            "id": "43222825-001"
          },
          "quantity": 400.0
        },
        {
          "unit": {
            "value": {
              "amount": 175060.0,
              "currency": "PYG"
            },
            "name": "Unidad"
          },
          "id": "4BPlsDfFsZ4%3D",
          "description": "Manguito",
          "classification": {
            "schema": "Catálogo de productos, bienes y servicios de la Dirección Nacional de Contrataciones Públicas del Paraguay",
            "uri": "https://www.contrataciones.gov.py/datos/api/v2/doc/catalogo/nivel-5/43222825-001",
            "description": "Catálogo de productos, bienes y servicios de la Dirección Nacional de Contrataciones Públicas del Paraguay Nivel 5, basado en UNSPSC",
            "id": "43222825-001"
          },
          "quantity": 200.0
        },
        {
          "unit": {
            "value": {
              "amount": 13200.0,
              "currency": "PYG"
            },
            "name": "Unidad"
          },
          "id": "IUHj1QnFFnU%3D",
          "description": "Brida de suspension",
          "classification": {
            "schema": "Catálogo de productos, bienes y servicios de la Dirección Nacional de Contrataciones Públicas del Paraguay",
            "uri": "https://www.contrataciones.gov.py/datos/api/v2/doc/catalogo/nivel-5/26121630-020",
            "description": "Catálogo de productos, bienes y servicios de la Dirección Nacional de Contrataciones Públicas del Paraguay Nivel 5, basado en UNSPSC",
            "id": "26121630-020"
          },
          "quantity": 1000.0
        },
        {
          "unit": {
            "value": {
              "amount": 63400.0,
              "currency": "PYG"
            },
            "name": "Unidad"
          },
          "id": "p9YzlRPdffc%3D",
          "description": "Ducto de acero ",
          "classification": {
            "schema": "Catálogo de productos, bienes y servicios de la Dirección Nacional de Contrataciones Públicas del Paraguay",
            "uri": "https://www.contrataciones.gov.py/datos/api/v2/doc/catalogo/nivel-5/39121207-002",
            "description": "Catálogo de productos, bienes y servicios de la Dirección Nacional de Contrataciones Públicas del Paraguay Nivel 5, basado en UNSPSC",
            "id": "39121207-002"
          },
          "quantity": 100.0
        },
        {
          "unit": {
            "value": {
              "amount": 48000.0,
              "currency": "PYG"
            },
            "name": "Unidad"
          },
          "id": "u0P39dRD0lE%3D",
          "description": "Conector para cables multipares",
          "classification": {
            "schema": "Catálogo de productos, bienes y servicios de la Dirección Nacional de Contrataciones Públicas del Paraguay",
            "uri": "https://www.contrataciones.gov.py/datos/api/v2/doc/catalogo/nivel-5/39121409-014",
            "description": "Catálogo de productos, bienes y servicios de la Dirección Nacional de Contrataciones Públicas del Paraguay Nivel 5, basado en UNSPSC",
            "id": "39121409-014"
          },
          "quantity": 100.0
        }
      ],
      "lots": [
        {
          "id": "nYZlDIKXpLc%3D",
          "items": [
            "yWlMMjl%2Ft9U%3D",
            "eBWjiICSWz0%3D",
            "1eZiY1phyuE%3D",
            "4BPlsDfFsZ4%3D",
            "IUHj1QnFFnU%3D",
            "p9YzlRPdffc%3D",
            "u0P39dRD0lE%3D"
          ],
          "title": "Lote 1"
        }
      ],
      "status": "active",
      "awardID": "274744-adquisicion-materiales-mantenimiento-red-planta-externa-ad-referendum-1"
    },
    {
      "documents": [
        {
          "id": "VyxRv5u5FaE%3D",
          "url": "https://www.contrataciones.gov.py/documentos/download/modificacion_contrato/VyxRv5u5FaE%253D",
          "format": "application/pdf",
          "language": "es",
          "documentType": "Adenda de Ampliación",
          "title": "Adenda de Ampliación"
        },
        {
          "id": "nzwg5Pwcg5Q%3D",
          "url": "https://www.contrataciones.gov.py/documentos/download/modificacion_contrato/nzwg5Pwcg5Q%253D",
          "format": "application/pdf",
          "language": "es",
          "documentType": "Resolución de Ampliación",
          "title": "Resolución de Ampliación"
        }
      ],
      "id": "274744-nelson-francisco-vera-quintana-2-ampliacion",
      "value": {
        "amount": null,
        "currency": "PYG"
      },
      "dncpAmendmentType": "Ampliación de Plazo",
      "title": "Contract Amendment: ADQUISICIÓN DE MATERIALES PARA MANTENIMIENTO DE LA RED DE PLANTA EXTERNA AD REFERENDUM",
      "dateSigned": null,
      "status": "active",
      "url": "https://www.contrataciones.gov.py/datos/id/modificaciones-contrato/274744-nelson-francisco-vera-quintana-2-ampliacion",
      "dncpContractCode": "_NO_APLICA_",
      "extendsContractID": "274744-nelson-francisco-vera-quintana-2",
      "awardID": "274744-adquisicion-materiales-mantenimiento-red-planta-externa-ad-referendum-1"
    }
  ],
  "tender": {
    "tenderPeriod": {
      "endDate": "2016-01-26T09:00:00-05:00",
      "startDate": null
    },
    "submissionMethod": [
      "written"
    ],
    "documents": [
      {
        "id": "IWib5gS3rac%3D",
        "url": "https://www.contrataciones.gov.py/documentos/download/convocatoria/IWib5gS3rac%253D",
        "format": "application/pdf",
        "language": "es",
        "documentType": "clarifications",
        "title": "Aclaraciones"
      },
      {
        "id": "ZcNbzUDA5hg%3D",
        "url": "https://www.contrataciones.gov.py/documentos/download/convocatoria/ZcNbzUDA5hg%253D",
        "format": "application/pdf",
        "language": "es",
        "documentType": "clarifications",
        "title": "Aclaraciones"
      },
      {
        "id": "E1vYTclO%2Bxc%3D",
        "url": "https://www.contrataciones.gov.py/documentos/download/convocatoria/E1vYTclO%252Bxc%253D",
        "format": "application/pdf",
        "language": "es",
        "documentType": "Adenda",
        "title": "Adenda"
      },
      {
        "id": "6VFY4aJOUS4%3D",
        "url": "https://www.contrataciones.gov.py/documentos/download/convocatoria/6VFY4aJOUS4%253D",
        "format": "application/pdf",
        "language": "es",
        "documentType": "Adenda",
        "title": "Adenda"
      },
      {
        "id": "Rbg4VdP2zw0%3D",
        "url": "https://www.contrataciones.gov.py/documentos/download/convocatoria/Rbg4VdP2zw0%253D",
        "format": "application/pdf",
        "language": "es",
        "documentType": "Condiciones Generales del Contrato - Bienes y Servicios",
        "title": "Condiciones Generales del Contrato - Bienes y Servicios"
      },
      {
        "id": "WA9bsqdhao0%3D",
        "url": "https://www.contrataciones.gov.py/documentos/download/convocatoria/WA9bsqdhao0%253D",
        "format": "application/pdf",
        "language": "es",
        "documentType": "Instrucción a los Oferentes - Bienes y Servicios",
        "title": "Instrucción a los Oferentes - Bienes y Servicios"
      },
      {
        "id": "OlROlefpxVs%3D",
        "url": "https://www.contrataciones.gov.py/documentos/download/convocatoria/OlROlefpxVs%253D",
        "format": "application/pdf",
        "language": "es",
        "documentType": "Nota de Observacion",
        "title": "Nota de Observacion"
      },
      {
        "id": "BHwD2%2BN6fZo%3D",
        "url": "https://www.contrataciones.gov.py/documentos/download/convocatoria/BHwD2%252BN6fZo%253D",
        "format": "application/zip",
        "language": "es",
        "documentType": "biddingDocuments",
        "title": "Pliego de bases y Condiciones"
      },
      {
        "id": "%2FEIAW%2Fw5oXI%3D",
        "url": "https://www.contrataciones.gov.py/documentos/download/convocatoria/%252FEIAW%252Fw5oXI%253D",
        "format": "application/pdf",
        "language": "es",
        "documentType": "Publicación en periódicos",
        "title": "Publicación en periódicos"
      }
    ],
    "enquiryPeriod": {
      "endDate": "2016-01-19T09:00:00-05:00"
    },
    "status": "complete",
    "hasEnquiries": false,
    "procuringEntity": {
      "contactPoint": {
        "telephone": "021444142",
        "email": "uoc@copaco.com.py",
        "name": "Norma Beatriz Fernández de Burgos"
      },
      "name": "Compañía Paraguaya de Comunicaciones (COPACO)"
    },
    "title": "ADQUISICIÓN DE MATERIALES PARA MANTENIMIENTO DE LA RED DE PLANTA EXTERNA AD REFERENDUM",
    "id": "274744-adquisicion-materiales-mantenimiento-red-planta-externa-ad-referendum-1",
    "value": {
      "amount": 940600832.0,
      "currency": "PYG"
    },
    "url": "https://www.contrataciones.gov.py/datos/id/convocatorias/274744-adquisicion-materiales-mantenimiento-red-planta-externa-ad-referendum-1",
    "items": [
      {
        "unit": {
          "value": {
            "amount": 163010.0,
            "currency": "PYG"
          },
          "name": "Unidad"
        },
        "id": "4ruk%2FtPXESNg3mM07iELNw%3D%3D",
        "description": "Caja terminal",
        "classification": {
          "id": "43222825-002",
          "uri": "https://www.contrataciones.gov.py/datos/api/v2/doc/catalogo/nivel-5/43222825-002",
          "scheme": "Catálogo de productos, bienes y servicios de la Dirección Nacional de Contrataciones Públicas del Paraguay",
          "description": "Catálogo de productos, bienes y servicios de la Dirección Nacional de Contrataciones Públicas del Paraguay Nivel 5, basado en UNSPSC"
        },
        "quantity": 200.0
      },
      {
        "unit": {
          "value": {
            "amount": 138750.0,
            "currency": "PYG"
          },
          "name": "Unidad"
        },
        "id": "w7g3jd%2FRAsNg3mM07iELNw%3D%3D",
        "description": "Caja terminal",
        "classification": {
          "id": "43222825-002",
          "uri": "https://www.contrataciones.gov.py/datos/api/v2/doc/catalogo/nivel-5/43222825-002",
          "scheme": "Catálogo de productos, bienes y servicios de la Dirección Nacional de Contrataciones Públicas del Paraguay",
          "description": "Catálogo de productos, bienes y servicios de la Dirección Nacional de Contrataciones Públicas del Paraguay Nivel 5, basado en UNSPSC"
        },
        "quantity": 400.0
      },
      {
        "unit": {
          "value": {
            "amount": 236.0,
            "currency": "PYG"
          },
          "name": "Unidad"
        },
        "id": "okvgy2YVEJVg3mM07iELNw%3D%3D",
        "description": "Conector para cables multipares",
        "classification": {
          "id": "39121409-014",
          "uri": "https://www.contrataciones.gov.py/datos/api/v2/doc/catalogo/nivel-5/39121409-014",
          "scheme": "Catálogo de productos, bienes y servicios de la Dirección Nacional de Contrataciones Públicas del Paraguay",
          "description": "Catálogo de productos, bienes y servicios de la Dirección Nacional de Contrataciones Públicas del Paraguay Nivel 5, basado en UNSPSC"
        },
        "quantity": 1000000.0
      },
      {
        "unit": {
          "value": {
            "amount": 117850.0,
            "currency": "PYG"
          },
          "name": "Unidad"
        },
        "id": "TRF2gO%2BkGrlg3mM07iELNw%3D%3D",
        "description": "Manguito",
        "classification": {
          "id": "43222825-001",
          "uri": "https://www.contrataciones.gov.py/datos/api/v2/doc/catalogo/nivel-5/43222825-001",
          "scheme": "Catálogo de productos, bienes y servicios de la Dirección Nacional de Contrataciones Públicas del Paraguay",
          "description": "Catálogo de productos, bienes y servicios de la Dirección Nacional de Contrataciones Públicas del Paraguay Nivel 5, basado en UNSPSC"
        },
        "quantity": 150.0
      },
      {
        "unit": {
          "value": {
            "amount": 581026.0,
            "currency": "PYG"
          },
          "name": "Unidad"
        },
        "id": "9K2r2yU3jURg3mM07iELNw%3D%3D",
        "description": "Manguito",
        "classification": {
          "id": "43222825-001",
          "uri": "https://www.contrataciones.gov.py/datos/api/v2/doc/catalogo/nivel-5/43222825-001",
          "scheme": "Catálogo de productos, bienes y servicios de la Dirección Nacional de Contrataciones Públicas del Paraguay",
          "description": "Catálogo de productos, bienes y servicios de la Dirección Nacional de Contrataciones Públicas del Paraguay Nivel 5, basado en UNSPSC"
        },
        "quantity": 150.0
      },
      {
        "unit": {
          "value": {
            "amount": 747033.0,
            "currency": "PYG"
          },
          "name": "Unidad"
        },
        "id": "kl26gyNzSKFg3mM07iELNw%3D%3D",
        "description": "Manguito",
        "classification": {
          "id": "43222825-001",
          "uri": "https://www.contrataciones.gov.py/datos/api/v2/doc/catalogo/nivel-5/43222825-001",
          "scheme": "Catálogo de productos, bienes y servicios de la Dirección Nacional de Contrataciones Públicas del Paraguay",
          "description": "Catálogo de productos, bienes y servicios de la Dirección Nacional de Contrataciones Públicas del Paraguay Nivel 5, basado en UNSPSC"
        },
        "quantity": 100.0
      },
      {
        "unit": {
          "value": {
            "amount": 747033.0,
            "currency": "PYG"
          },
          "name": "Unidad"
        },
        "id": "YyvSo6JGH3pg3mM07iELNw%3D%3D",
        "description": "Manguito",
        "classification": {
          "id": "43222825-001",
          "uri": "https://www.contrataciones.gov.py/datos/api/v2/doc/catalogo/nivel-5/43222825-001",
          "scheme": "Catálogo de productos, bienes y servicios de la Dirección Nacional de Contrataciones Públicas del Paraguay",
          "description": "Catálogo de productos, bienes y servicios de la Dirección Nacional de Contrataciones Públicas del Paraguay Nivel 5, basado en UNSPSC"
        },
        "quantity": 50.0
      },
      {
        "unit": {
          "value": {
            "amount": 996044.0,
            "currency": "PYG"
          },
          "name": "Unidad"
        },
        "id": "nrfO75Zbl21g3mM07iELNw%3D%3D",
        "description": "Manguito",
        "classification": {
          "id": "43222825-001",
          "uri": "https://www.contrataciones.gov.py/datos/api/v2/doc/catalogo/nivel-5/43222825-001",
          "scheme": "Catálogo de productos, bienes y servicios de la Dirección Nacional de Contrataciones Públicas del Paraguay",
          "description": "Catálogo de productos, bienes y servicios de la Dirección Nacional de Contrataciones Públicas del Paraguay Nivel 5, basado en UNSPSC"
        },
        "quantity": 50.0
      },
      {
        "unit": {
          "value": {
            "amount": 232943.0,
            "currency": "PYG"
          },
          "name": "Unidad"
        },
        "id": "5em1OLG1aDpg3mM07iELNw%3D%3D",
        "description": "Manguito",
        "classification": {
          "id": "43222825-001",
          "uri": "https://www.contrataciones.gov.py/datos/api/v2/doc/catalogo/nivel-5/43222825-001",
          "scheme": "Catálogo de productos, bienes y servicios de la Dirección Nacional de Contrataciones Públicas del Paraguay",
          "description": "Catálogo de productos, bienes y servicios de la Dirección Nacional de Contrataciones Públicas del Paraguay Nivel 5, basado en UNSPSC"
        },
        "quantity": 400.0
      },
      {
        "unit": {
          "value": {
            "amount": 243243.0,
            "currency": "PYG"
          },
          "name": "Unidad"
        },
        "id": "KFtswxGOjLdg3mM07iELNw%3D%3D",
        "description": "Manguito",
        "classification": {
          "id": "43222825-001",
          "uri": "https://www.contrataciones.gov.py/datos/api/v2/doc/catalogo/nivel-5/43222825-001",
          "scheme": "Catálogo de productos, bienes y servicios de la Dirección Nacional de Contrataciones Públicas del Paraguay",
          "description": "Catálogo de productos, bienes y servicios de la Dirección Nacional de Contrataciones Públicas del Paraguay Nivel 5, basado en UNSPSC"
        },
        "quantity": 200.0
      },
      {
        "unit": {
          "value": {
            "amount": 190000.0,
            "currency": "PYG"
          },
          "name": "Unidad"
        },
        "id": "OxSDU8hziCtg3mM07iELNw%3D%3D",
        "description": "Espiral preformado",
        "classification": {
          "id": "26121630-016",
          "uri": "https://www.contrataciones.gov.py/datos/api/v2/doc/catalogo/nivel-5/26121630-016",
          "scheme": "Catálogo de productos, bienes y servicios de la Dirección Nacional de Contrataciones Públicas del Paraguay",
          "description": "Catálogo de productos, bienes y servicios de la Dirección Nacional de Contrataciones Públicas del Paraguay Nivel 5, basado en UNSPSC"
        },
        "quantity": 300.0
      },
      {
        "unit": {
          "value": {
            "amount": 18620.0,
            "currency": "PYG"
          },
          "name": "Unidad"
        },
        "id": "u2Ed6DONw21g3mM07iELNw%3D%3D",
        "description": "Espiral preformado",
        "classification": {
          "id": "26121630-016",
          "uri": "https://www.contrataciones.gov.py/datos/api/v2/doc/catalogo/nivel-5/26121630-016",
          "scheme": "Catálogo de productos, bienes y servicios de la Dirección Nacional de Contrataciones Públicas del Paraguay",
          "description": "Catálogo de productos, bienes y servicios de la Dirección Nacional de Contrataciones Públicas del Paraguay Nivel 5, basado en UNSPSC"
        },
        "quantity": 300.0
      },
      {
        "unit": {
          "value": {
            "amount": 10100.0,
            "currency": "PYG"
          },
          "name": "Unidad"
        },
        "id": "ILXt%2BLHy0yJg3mM07iELNw%3D%3D",
        "description": "Espiral preformado",
        "classification": {
          "id": "26121630-016",
          "uri": "https://www.contrataciones.gov.py/datos/api/v2/doc/catalogo/nivel-5/26121630-016",
          "scheme": "Catálogo de productos, bienes y servicios de la Dirección Nacional de Contrataciones Públicas del Paraguay",
          "description": "Catálogo de productos, bienes y servicios de la Dirección Nacional de Contrataciones Públicas del Paraguay Nivel 5, basado en UNSPSC"
        },
        "quantity": 250.0
      },
      {
        "unit": {
          "value": {
            "amount": 10100.0,
            "currency": "PYG"
          },
          "name": "Unidad"
        },
        "id": "MLrv7mD2kz5g3mM07iELNw%3D%3D",
        "description": "Espiral preformado",
        "classification": {
          "id": "26121630-016",
          "uri": "https://www.contrataciones.gov.py/datos/api/v2/doc/catalogo/nivel-5/26121630-016",
          "scheme": "Catálogo de productos, bienes y servicios de la Dirección Nacional de Contrataciones Públicas del Paraguay",
          "description": "Catálogo de productos, bienes y servicios de la Dirección Nacional de Contrataciones Públicas del Paraguay Nivel 5, basado en UNSPSC"
        },
        "quantity": 250.0
      },
      {
        "unit": {
          "value": {
            "amount": 23215.0,
            "currency": "PYG"
          },
          "name": "Unidad"
        },
        "id": "yNfFLbAP53Bg3mM07iELNw%3D%3D",
        "description": "Espiral preformado",
        "classification": {
          "id": "26121630-016",
          "uri": "https://www.contrataciones.gov.py/datos/api/v2/doc/catalogo/nivel-5/26121630-016",
          "scheme": "Catálogo de productos, bienes y servicios de la Dirección Nacional de Contrataciones Públicas del Paraguay",
          "description": "Catálogo de productos, bienes y servicios de la Dirección Nacional de Contrataciones Públicas del Paraguay Nivel 5, basado en UNSPSC"
        },
        "quantity": 200.0
      },
      {
        "unit": {
          "value": {
            "amount": 12500.0,
            "currency": "PYG"
          },
          "name": "Unidad"
        },
        "id": "hbVOtNex%2FP5g3mM07iELNw%3D%3D",
        "description": "Espiral preformado",
        "classification": {
          "id": "26121630-016",
          "uri": "https://www.contrataciones.gov.py/datos/api/v2/doc/catalogo/nivel-5/26121630-016",
          "scheme": "Catálogo de productos, bienes y servicios de la Dirección Nacional de Contrataciones Públicas del Paraguay",
          "description": "Catálogo de productos, bienes y servicios de la Dirección Nacional de Contrataciones Públicas del Paraguay Nivel 5, basado en UNSPSC"
        },
        "quantity": 200.0
      },
      {
        "unit": {
          "value": {
            "amount": 13260.0,
            "currency": "PYG"
          },
          "name": "Unidad"
        },
        "id": "OHgEq3Xhth9g3mM07iELNw%3D%3D",
        "description": "Brida de suspension",
        "classification": {
          "id": "26121630-020",
          "uri": "https://www.contrataciones.gov.py/datos/api/v2/doc/catalogo/nivel-5/26121630-020",
          "scheme": "Catálogo de productos, bienes y servicios de la Dirección Nacional de Contrataciones Públicas del Paraguay",
          "description": "Catálogo de productos, bienes y servicios de la Dirección Nacional de Contrataciones Públicas del Paraguay Nivel 5, basado en UNSPSC"
        },
        "quantity": 1000.0
      },
      {
        "unit": {
          "value": {
            "amount": 63050.0,
            "currency": "PYG"
          },
          "name": "Unidad"
        },
        "id": "oMrQJTbwkI1g3mM07iELNw%3D%3D",
        "description": "Ducto de acero ",
        "classification": {
          "id": "39121207-002",
          "uri": "https://www.contrataciones.gov.py/datos/api/v2/doc/catalogo/nivel-5/39121207-002",
          "scheme": "Catálogo de productos, bienes y servicios de la Dirección Nacional de Contrataciones Públicas del Paraguay",
          "description": "Catálogo de productos, bienes y servicios de la Dirección Nacional de Contrataciones Públicas del Paraguay Nivel 5, basado en UNSPSC"
        },
        "quantity": 100.0
      },
      {
        "unit": {
          "value": {
            "amount": 650.0,
            "currency": "PYG"
          },
          "name": "Unidad"
        },
        "id": "NKJr5TxzHx1g3mM07iELNw%3D%3D",
        "description": "Guardacabo de acero",
        "classification": {
          "id": "31162504-002",
          "uri": "https://www.contrataciones.gov.py/datos/api/v2/doc/catalogo/nivel-5/31162504-002",
          "scheme": "Catálogo de productos, bienes y servicios de la Dirección Nacional de Contrataciones Públicas del Paraguay",
          "description": "Catálogo de productos, bienes y servicios de la Dirección Nacional de Contrataciones Públicas del Paraguay Nivel 5, basado en UNSPSC"
        },
        "quantity": 200.0
      },
      {
        "unit": {
          "value": {
            "amount": 650.0,
            "currency": "PYG"
          },
          "name": "Unidad"
        },
        "id": "4ROGiavwbbRg3mM07iELNw%3D%3D",
        "description": "Guardacabo de acero",
        "classification": {
          "id": "31162504-002",
          "uri": "https://www.contrataciones.gov.py/datos/api/v2/doc/catalogo/nivel-5/31162504-002",
          "scheme": "Catálogo de productos, bienes y servicios de la Dirección Nacional de Contrataciones Públicas del Paraguay",
          "description": "Catálogo de productos, bienes y servicios de la Dirección Nacional de Contrataciones Públicas del Paraguay Nivel 5, basado en UNSPSC"
        },
        "quantity": 200.0
      },
      {
        "unit": {
          "value": {
            "amount": 975.0,
            "currency": "PYG"
          },
          "name": "Unidad"
        },
        "id": "9GNQoc0yZdVg3mM07iELNw%3D%3D",
        "description": "Guardacabo de acero",
        "classification": {
          "id": "31162504-002",
          "uri": "https://www.contrataciones.gov.py/datos/api/v2/doc/catalogo/nivel-5/31162504-002",
          "scheme": "Catálogo de productos, bienes y servicios de la Dirección Nacional de Contrataciones Públicas del Paraguay",
          "description": "Catálogo de productos, bienes y servicios de la Dirección Nacional de Contrataciones Públicas del Paraguay Nivel 5, basado en UNSPSC"
        },
        "quantity": 500.0
      },
      {
        "unit": {
          "value": {
            "amount": 780.0,
            "currency": "PYG"
          },
          "name": "Unidad"
        },
        "id": "jRQTDVKt2Itg3mM07iELNw%3D%3D",
        "description": "Guardacabo de acero",
        "classification": {
          "id": "31162504-002",
          "uri": "https://www.contrataciones.gov.py/datos/api/v2/doc/catalogo/nivel-5/31162504-002",
          "scheme": "Catálogo de productos, bienes y servicios de la Dirección Nacional de Contrataciones Públicas del Paraguay",
          "description": "Catálogo de productos, bienes y servicios de la Dirección Nacional de Contrataciones Públicas del Paraguay Nivel 5, basado en UNSPSC"
        },
        "quantity": 500.0
      },
      {
        "unit": {
          "value": {
            "amount": 1040.0,
            "currency": "PYG"
          },
          "name": "Unidad"
        },
        "id": "0KCGTin%2BsNNg3mM07iELNw%3D%3D",
        "description": "Guardacabo de acero",
        "classification": {
          "id": "31162504-002",
          "uri": "https://www.contrataciones.gov.py/datos/api/v2/doc/catalogo/nivel-5/31162504-002",
          "scheme": "Catálogo de productos, bienes y servicios de la Dirección Nacional de Contrataciones Públicas del Paraguay",
          "description": "Catálogo de productos, bienes y servicios de la Dirección Nacional de Contrataciones Públicas del Paraguay Nivel 5, basado en UNSPSC"
        },
        "quantity": 500.0
      },
      {
        "unit": {
          "value": {
            "amount": 650.0,
            "currency": "PYG"
          },
          "name": "Unidad"
        },
        "id": "7OfMVXLB6%2FNg3mM07iELNw%3D%3D",
        "description": "Prensita para empalme",
        "classification": {
          "id": "39121701-002",
          "uri": "https://www.contrataciones.gov.py/datos/api/v2/doc/catalogo/nivel-5/39121701-002",
          "scheme": "Catálogo de productos, bienes y servicios de la Dirección Nacional de Contrataciones Públicas del Paraguay",
          "description": "Catálogo de productos, bienes y servicios de la Dirección Nacional de Contrataciones Públicas del Paraguay Nivel 5, basado en UNSPSC"
        },
        "quantity": 1000.0
      },
      {
        "unit": {
          "value": {
            "amount": 1300.0,
            "currency": "PYG"
          },
          "name": "Unidad"
        },
        "id": "Z7tiaOHUdrFg3mM07iELNw%3D%3D",
        "description": "Prensita para empalme",
        "classification": {
          "id": "39121701-002",
          "uri": "https://www.contrataciones.gov.py/datos/api/v2/doc/catalogo/nivel-5/39121701-002",
          "scheme": "Catálogo de productos, bienes y servicios de la Dirección Nacional de Contrataciones Públicas del Paraguay",
          "description": "Catálogo de productos, bienes y servicios de la Dirección Nacional de Contrataciones Públicas del Paraguay Nivel 5, basado en UNSPSC"
        },
        "quantity": 1000.0
      },
      {
        "unit": {
          "value": {
            "amount": 1950.0,
            "currency": "PYG"
          },
          "name": "Unidad"
        },
        "id": "D%2FsA244J1fJg3mM07iELNw%3D%3D",
        "description": "Prensita para empalme",
        "classification": {
          "id": "39121701-002",
          "uri": "https://www.contrataciones.gov.py/datos/api/v2/doc/catalogo/nivel-5/39121701-002",
          "scheme": "Catálogo de productos, bienes y servicios de la Dirección Nacional de Contrataciones Públicas del Paraguay",
          "description": "Catálogo de productos, bienes y servicios de la Dirección Nacional de Contrataciones Públicas del Paraguay Nivel 5, basado en UNSPSC"
        },
        "quantity": 1000.0
      },
      {
        "unit": {
          "value": {
            "amount": 18200.0,
            "currency": "PYG"
          },
          "name": "Unidad"
        },
        "id": "Y7U7H9aYpgNg3mM07iELNw%3D%3D",
        "description": "Disco de corte para amoladora",
        "classification": {
          "id": "20101712-998",
          "uri": "https://www.contrataciones.gov.py/datos/api/v2/doc/catalogo/nivel-5/20101712-998",
          "scheme": "Catálogo de productos, bienes y servicios de la Dirección Nacional de Contrataciones Públicas del Paraguay",
          "description": "Catálogo de productos, bienes y servicios de la Dirección Nacional de Contrataciones Públicas del Paraguay Nivel 5, basado en UNSPSC"
        },
        "quantity": 20.0
      },
      {
        "unit": {
          "value": {
            "amount": 23400.0,
            "currency": "PYG"
          },
          "name": "Kilogramos"
        },
        "id": "oxOj7JBTbARg3mM07iELNw%3D%3D",
        "description": "Electrodo",
        "classification": {
          "id": "39121436-001",
          "uri": "https://www.contrataciones.gov.py/datos/api/v2/doc/catalogo/nivel-5/39121436-001",
          "scheme": "Catálogo de productos, bienes y servicios de la Dirección Nacional de Contrataciones Públicas del Paraguay",
          "description": "Catálogo de productos, bienes y servicios de la Dirección Nacional de Contrataciones Públicas del Paraguay Nivel 5, basado en UNSPSC"
        },
        "quantity": 50.0
      },
      {
        "unit": {
          "value": {
            "amount": 6500.0,
            "currency": "PYG"
          },
          "name": "Unidad"
        },
        "id": "JwGmWbsT1oBg3mM07iELNw%3D%3D",
        "description": "Hoja de sierra",
        "classification": {
          "id": "27112802-001",
          "uri": "https://www.contrataciones.gov.py/datos/api/v2/doc/catalogo/nivel-5/27112802-001",
          "scheme": "Catálogo de productos, bienes y servicios de la Dirección Nacional de Contrataciones Públicas del Paraguay",
          "description": "Catálogo de productos, bienes y servicios de la Dirección Nacional de Contrataciones Públicas del Paraguay Nivel 5, basado en UNSPSC"
        },
        "quantity": 50.0
      },
      {
        "unit": {
          "value": {
            "amount": 1794.0,
            "currency": "PYG"
          },
          "name": "Metros"
        },
        "id": "1L%2F14%2BQoalNg3mM07iELNw%3D%3D",
        "description": "Cable Telefonico (cruzada)",
        "classification": {
          "id": "26121616-006",
          "uri": "https://www.contrataciones.gov.py/datos/api/v2/doc/catalogo/nivel-5/26121616-006",
          "scheme": "Catálogo de productos, bienes y servicios de la Dirección Nacional de Contrataciones Públicas del Paraguay",
          "description": "Catálogo de productos, bienes y servicios de la Dirección Nacional de Contrataciones Públicas del Paraguay Nivel 5, basado en UNSPSC"
        },
        "quantity": 500.0
      },
      {
        "unit": {
          "value": {
            "amount": 2751.0,
            "currency": "PYG"
          },
          "name": "Metros"
        },
        "id": "KgoW%2BdSUda1g3mM07iELNw%3D%3D",
        "description": "Cable Telefonico (cruzada)",
        "classification": {
          "id": "26121616-006",
          "uri": "https://www.contrataciones.gov.py/datos/api/v2/doc/catalogo/nivel-5/26121616-006",
          "scheme": "Catálogo de productos, bienes y servicios de la Dirección Nacional de Contrataciones Públicas del Paraguay",
          "description": "Catálogo de productos, bienes y servicios de la Dirección Nacional de Contrataciones Públicas del Paraguay Nivel 5, basado en UNSPSC"
        },
        "quantity": 500.0
      },
      {
        "unit": {
          "value": {
            "amount": 4545.0,
            "currency": "PYG"
          },
          "name": "Metros"
        },
        "id": "DEjqXgqsp0Vg3mM07iELNw%3D%3D",
        "description": "Cable Telefonico (cruzada)",
        "classification": {
          "id": "26121616-006",
          "uri": "https://www.contrataciones.gov.py/datos/api/v2/doc/catalogo/nivel-5/26121616-006",
          "scheme": "Catálogo de productos, bienes y servicios de la Dirección Nacional de Contrataciones Públicas del Paraguay",
          "description": "Catálogo de productos, bienes y servicios de la Dirección Nacional de Contrataciones Públicas del Paraguay Nivel 5, basado en UNSPSC"
        },
        "quantity": 500.0
      },
      {
        "unit": {
          "value": {
            "amount": 3900.0,
            "currency": "PYG"
          },
          "name": "Unidad"
        },
        "id": "KSORJTXQrwxg3mM07iELNw%3D%3D",
        "description": "Cinta aisladora electrica autovulcanizante",
        "classification": {
          "id": "31201502-001",
          "uri": "https://www.contrataciones.gov.py/datos/api/v2/doc/catalogo/nivel-5/31201502-001",
          "scheme": "Catálogo de productos, bienes y servicios de la Dirección Nacional de Contrataciones Públicas del Paraguay",
          "description": "Catálogo de productos, bienes y servicios de la Dirección Nacional de Contrataciones Públicas del Paraguay Nivel 5, basado en UNSPSC"
        },
        "quantity": 100.0
      },
      {
        "unit": {
          "value": {
            "amount": 14300.0,
            "currency": "PYG"
          },
          "name": "Unidad"
        },
        "id": "ZoNQ0XzP6aNg3mM07iELNw%3D%3D",
        "description": "Tinner",
        "classification": {
          "id": "31211803-005",
          "uri": "https://www.contrataciones.gov.py/datos/api/v2/doc/catalogo/nivel-5/31211803-005",
          "scheme": "Catálogo de productos, bienes y servicios de la Dirección Nacional de Contrataciones Públicas del Paraguay",
          "description": "Catálogo de productos, bienes y servicios de la Dirección Nacional de Contrataciones Públicas del Paraguay Nivel 5, basado en UNSPSC"
        },
        "quantity": 50.0
      },
      {
        "unit": {
          "value": {
            "amount": 260000.0,
            "currency": "PYG"
          },
          "name": "Unidad"
        },
        "id": "QmGBH2NIRXhg3mM07iELNw%3D%3D",
        "description": "Lampara Halogena ",
        "classification": {
          "id": "39101602-007",
          "uri": "https://www.contrataciones.gov.py/datos/api/v2/doc/catalogo/nivel-5/39101602-007",
          "scheme": "Catálogo de productos, bienes y servicios de la Dirección Nacional de Contrataciones Públicas del Paraguay",
          "description": "Catálogo de productos, bienes y servicios de la Dirección Nacional de Contrataciones Públicas del Paraguay Nivel 5, basado en UNSPSC"
        },
        "quantity": 5.0
      },
      {
        "unit": {
          "value": {
            "amount": 11050.0,
            "currency": "PYG"
          },
          "name": "Unidad"
        },
        "id": "c2451IOVFrJg3mM07iELNw%3D%3D",
        "description": "Condensador",
        "classification": {
          "id": "39121004-027",
          "uri": "https://www.contrataciones.gov.py/datos/api/v2/doc/catalogo/nivel-5/39121004-027",
          "scheme": "Catálogo de productos, bienes y servicios de la Dirección Nacional de Contrataciones Públicas del Paraguay",
          "description": "Catálogo de productos, bienes y servicios de la Dirección Nacional de Contrataciones Públicas del Paraguay Nivel 5, basado en UNSPSC"
        },
        "quantity": 200.0
      },
      {
        "unit": {
          "value": {
            "amount": 910.0,
            "currency": "PYG"
          },
          "name": "Unidad"
        },
        "id": "Jifn8OT9duNg3mM07iELNw%3D%3D",
        "description": "Condensador",
        "classification": {
          "id": "39121004-027",
          "uri": "https://www.contrataciones.gov.py/datos/api/v2/doc/catalogo/nivel-5/39121004-027",
          "scheme": "Catálogo de productos, bienes y servicios de la Dirección Nacional de Contrataciones Públicas del Paraguay",
          "description": "Catálogo de productos, bienes y servicios de la Dirección Nacional de Contrataciones Públicas del Paraguay Nivel 5, basado en UNSPSC"
        },
        "quantity": 200.0
      },
      {
        "unit": {
          "value": {
            "amount": 2600.0,
            "currency": "PYG"
          },
          "name": "Unidad"
        },
        "id": "SIezvjJD%2Fztg3mM07iELNw%3D%3D",
        "description": "Condensador",
        "classification": {
          "id": "39121004-027",
          "uri": "https://www.contrataciones.gov.py/datos/api/v2/doc/catalogo/nivel-5/39121004-027",
          "scheme": "Catálogo de productos, bienes y servicios de la Dirección Nacional de Contrataciones Públicas del Paraguay",
          "description": "Catálogo de productos, bienes y servicios de la Dirección Nacional de Contrataciones Públicas del Paraguay Nivel 5, basado en UNSPSC"
        },
        "quantity": 200.0
      },
      {
        "unit": {
          "value": {
            "amount": 910.0,
            "currency": "PYG"
          },
          "name": "Unidad"
        },
        "id": "Sm1ksgmEW%2BFg3mM07iELNw%3D%3D",
        "description": "Condensador",
        "classification": {
          "id": "39121004-027",
          "uri": "https://www.contrataciones.gov.py/datos/api/v2/doc/catalogo/nivel-5/39121004-027",
          "scheme": "Catálogo de productos, bienes y servicios de la Dirección Nacional de Contrataciones Públicas del Paraguay",
          "description": "Catálogo de productos, bienes y servicios de la Dirección Nacional de Contrataciones Públicas del Paraguay Nivel 5, basado en UNSPSC"
        },
        "quantity": 200.0
      },
      {
        "unit": {
          "value": {
            "amount": 13000.0,
            "currency": "PYG"
          },
          "name": "Unidad"
        },
        "id": "kywEJ%2B%2FG%2Fdlg3mM07iELNw%3D%3D",
        "description": "Circuito intregrado para redes",
        "classification": {
          "id": "32101620-002",
          "uri": "https://www.contrataciones.gov.py/datos/api/v2/doc/catalogo/nivel-5/32101620-002",
          "scheme": "Catálogo de productos, bienes y servicios de la Dirección Nacional de Contrataciones Públicas del Paraguay",
          "description": "Catálogo de productos, bienes y servicios de la Dirección Nacional de Contrataciones Públicas del Paraguay Nivel 5, basado en UNSPSC"
        },
        "quantity": 200.0
      },
      {
        "unit": {
          "value": {
            "amount": 13000.0,
            "currency": "PYG"
          },
          "name": "Unidad"
        },
        "id": "ULSLxhgb%2BHRg3mM07iELNw%3D%3D",
        "description": "Transistor de efecto de campo (FET)",
        "classification": {
          "id": "32111602-001",
          "uri": "https://www.contrataciones.gov.py/datos/api/v2/doc/catalogo/nivel-5/32111602-001",
          "scheme": "Catálogo de productos, bienes y servicios de la Dirección Nacional de Contrataciones Públicas del Paraguay",
          "description": "Catálogo de productos, bienes y servicios de la Dirección Nacional de Contrataciones Públicas del Paraguay Nivel 5, basado en UNSPSC"
        },
        "quantity": 200.0
      },
      {
        "unit": {
          "value": {
            "amount": 50.0,
            "currency": "PYG"
          },
          "name": "Unidad"
        },
        "id": "BkH%2F40mblrNg3mM07iELNw%3D%3D",
        "description": "Resistencia electrica",
        "classification": {
          "id": "41111943-001",
          "uri": "https://www.contrataciones.gov.py/datos/api/v2/doc/catalogo/nivel-5/41111943-001",
          "scheme": "Catálogo de productos, bienes y servicios de la Dirección Nacional de Contrataciones Públicas del Paraguay",
          "description": "Catálogo de productos, bienes y servicios de la Dirección Nacional de Contrataciones Públicas del Paraguay Nivel 5, basado en UNSPSC"
        },
        "quantity": 200.0
      },
      {
        "unit": {
          "value": {
            "amount": 1800.0,
            "currency": "PYG"
          },
          "name": "Unidad"
        },
        "id": "Hs0jNALrErRg3mM07iELNw%3D%3D",
        "description": "Transistor de efecto de campo (FET)",
        "classification": {
          "id": "32111602-001",
          "uri": "https://www.contrataciones.gov.py/datos/api/v2/doc/catalogo/nivel-5/32111602-001",
          "scheme": "Catálogo de productos, bienes y servicios de la Dirección Nacional de Contrataciones Públicas del Paraguay",
          "description": "Catálogo de productos, bienes y servicios de la Dirección Nacional de Contrataciones Públicas del Paraguay Nivel 5, basado en UNSPSC"
        },
        "quantity": 50.0
      },
      {
        "unit": {
          "value": {
            "amount": 1300.0,
            "currency": "PYG"
          },
          "name": "Unidad"
        },
        "id": "1UGYt%2BNOAOFg3mM07iELNw%3D%3D",
        "description": "Transistor de efecto de campo (FET)",
        "classification": {
          "id": "32111602-001",
          "uri": "https://www.contrataciones.gov.py/datos/api/v2/doc/catalogo/nivel-5/32111602-001",
          "scheme": "Catálogo de productos, bienes y servicios de la Dirección Nacional de Contrataciones Públicas del Paraguay",
          "description": "Catálogo de productos, bienes y servicios de la Dirección Nacional de Contrataciones Públicas del Paraguay Nivel 5, basado en UNSPSC"
        },
        "quantity": 50.0
      },
      {
        "unit": {
          "value": {
            "amount": 1300.0,
            "currency": "PYG"
          },
          "name": "Unidad"
        },
        "id": "YCt9AbOliPlg3mM07iELNw%3D%3D",
        "description": "Transistor de efecto de campo (FET)",
        "classification": {
          "id": "32111602-001",
          "uri": "https://www.contrataciones.gov.py/datos/api/v2/doc/catalogo/nivel-5/32111602-001",
          "scheme": "Catálogo de productos, bienes y servicios de la Dirección Nacional de Contrataciones Públicas del Paraguay",
          "description": "Catálogo de productos, bienes y servicios de la Dirección Nacional de Contrataciones Públicas del Paraguay Nivel 5, basado en UNSPSC"
        },
        "quantity": 50.0
      },
      {
        "unit": {
          "value": {
            "amount": 40000.0,
            "currency": "PYG"
          },
          "name": "Unidad"
        },
        "id": "jiyk5HJylfdg3mM07iELNw%3D%3D",
        "description": "Diodo",
        "classification": {
          "id": "32111511-001",
          "uri": "https://www.contrataciones.gov.py/datos/api/v2/doc/catalogo/nivel-5/32111511-001",
          "scheme": "Catálogo de productos, bienes y servicios de la Dirección Nacional de Contrataciones Públicas del Paraguay",
          "description": "Catálogo de productos, bienes y servicios de la Dirección Nacional de Contrataciones Públicas del Paraguay Nivel 5, basado en UNSPSC"
        },
        "quantity": 50.0
      },
      {
        "unit": {
          "value": {
            "amount": 39000.0,
            "currency": "PYG"
          },
          "name": "Litros"
        },
        "id": "AlNgXMgitgVg3mM07iELNw%3D%3D",
        "description": "Pintura sintetica",
        "classification": {
          "id": "31211508-001",
          "uri": "https://www.contrataciones.gov.py/datos/api/v2/doc/catalogo/nivel-5/31211508-001",
          "scheme": "Catálogo de productos, bienes y servicios de la Dirección Nacional de Contrataciones Públicas del Paraguay",
          "description": "Catálogo de productos, bienes y servicios de la Dirección Nacional de Contrataciones Públicas del Paraguay Nivel 5, basado en UNSPSC"
        },
        "quantity": 50.0
      },
      {
        "unit": {
          "value": {
            "amount": 26000.0,
            "currency": "PYG"
          },
          "name": "Litros"
        },
        "id": "DYfpugvFVaJg3mM07iELNw%3D%3D",
        "description": "Pintura antioxido",
        "classification": {
          "id": "31211508-006",
          "uri": "https://www.contrataciones.gov.py/datos/api/v2/doc/catalogo/nivel-5/31211508-006",
          "scheme": "Catálogo de productos, bienes y servicios de la Dirección Nacional de Contrataciones Públicas del Paraguay",
          "description": "Catálogo de productos, bienes y servicios de la Dirección Nacional de Contrataciones Públicas del Paraguay Nivel 5, basado en UNSPSC"
        },
        "quantity": 50.0
      },
      {
        "unit": {
          "value": {
            "amount": 400000.0,
            "currency": "PYG"
          },
          "name": "Unidad"
        },
        "id": "DYnB13JUiVJg3mM07iELNw%3D%3D",
        "description": "Caja de conexion para modulos LSA ",
        "classification": {
          "id": "43211601-008",
          "uri": "https://www.contrataciones.gov.py/datos/api/v2/doc/catalogo/nivel-5/43211601-008",
          "scheme": "Catálogo de productos, bienes y servicios de la Dirección Nacional de Contrataciones Públicas del Paraguay",
          "description": "Catálogo de productos, bienes y servicios de la Dirección Nacional de Contrataciones Públicas del Paraguay Nivel 5, basado en UNSPSC"
        },
        "quantity": 100.0
      },
      {
        "unit": {
          "value": {
            "amount": 350000.0,
            "currency": "PYG"
          },
          "name": "Unidad"
        },
        "id": "dfgcKOBH%2B6dg3mM07iELNw%3D%3D",
        "description": "Caja de conexion para modulos LSA ",
        "classification": {
          "id": "43211601-008",
          "uri": "https://www.contrataciones.gov.py/datos/api/v2/doc/catalogo/nivel-5/43211601-008",
          "scheme": "Catálogo de productos, bienes y servicios de la Dirección Nacional de Contrataciones Públicas del Paraguay",
          "description": "Catálogo de productos, bienes y servicios de la Dirección Nacional de Contrataciones Públicas del Paraguay Nivel 5, basado en UNSPSC"
        },
        "quantity": 100.0
      },
      {
        "unit": {
          "value": {
            "amount": 35000.0,
            "currency": "PYG"
          },
          "name": "Unidad"
        },
        "id": "3Uew26jzdZhg3mM07iELNw%3D%3D",
        "description": "Conector para cables multipares",
        "classification": {
          "id": "39121409-014",
          "uri": "https://www.contrataciones.gov.py/datos/api/v2/doc/catalogo/nivel-5/39121409-014",
          "scheme": "Catálogo de productos, bienes y servicios de la Dirección Nacional de Contrataciones Públicas del Paraguay",
          "description": "Catálogo de productos, bienes y servicios de la Dirección Nacional de Contrataciones Públicas del Paraguay Nivel 5, basado en UNSPSC"
        },
        "quantity": 100.0
      },
      {
        "unit": {
          "value": {
            "amount": 35000.0,
            "currency": "PYG"
          },
          "name": "Unidad"
        },
        "id": "r%2F06Emgq7wRg3mM07iELNw%3D%3D",
        "description": "Conector para cables multipares",
        "classification": {
          "id": "39121409-014",
          "uri": "https://www.contrataciones.gov.py/datos/api/v2/doc/catalogo/nivel-5/39121409-014",
          "scheme": "Catálogo de productos, bienes y servicios de la Dirección Nacional de Contrataciones Públicas del Paraguay",
          "description": "Catálogo de productos, bienes y servicios de la Dirección Nacional de Contrataciones Públicas del Paraguay Nivel 5, basado en UNSPSC"
        },
        "quantity": 100.0
      },
      {
        "unit": {
          "value": {
            "amount": 35000.0,
            "currency": "PYG"
          },
          "name": "Unidad"
        },
        "id": "B4lrQXBcdUdg3mM07iELNw%3D%3D",
        "description": "Conector para cables multipares",
        "classification": {
          "id": "39121409-014",
          "uri": "https://www.contrataciones.gov.py/datos/api/v2/doc/catalogo/nivel-5/39121409-014",
          "scheme": "Catálogo de productos, bienes y servicios de la Dirección Nacional de Contrataciones Públicas del Paraguay",
          "description": "Catálogo de productos, bienes y servicios de la Dirección Nacional de Contrataciones Públicas del Paraguay Nivel 5, basado en UNSPSC"
        },
        "quantity": 100.0
      }
    ],
    "lots": [
      {
        "id": "nYZlDIKXpLc%3D",
        "items": [
          "4ruk%2FtPXESNg3mM07iELNw%3D%3D",
          "w7g3jd%2FRAsNg3mM07iELNw%3D%3D",
          "okvgy2YVEJVg3mM07iELNw%3D%3D",
          "TRF2gO%2BkGrlg3mM07iELNw%3D%3D",
          "9K2r2yU3jURg3mM07iELNw%3D%3D",
          "kl26gyNzSKFg3mM07iELNw%3D%3D",
          "YyvSo6JGH3pg3mM07iELNw%3D%3D",
          "nrfO75Zbl21g3mM07iELNw%3D%3D",
          "5em1OLG1aDpg3mM07iELNw%3D%3D",
          "KFtswxGOjLdg3mM07iELNw%3D%3D",
          "OxSDU8hziCtg3mM07iELNw%3D%3D",
          "u2Ed6DONw21g3mM07iELNw%3D%3D",
          "ILXt%2BLHy0yJg3mM07iELNw%3D%3D",
          "MLrv7mD2kz5g3mM07iELNw%3D%3D",
          "yNfFLbAP53Bg3mM07iELNw%3D%3D",
          "hbVOtNex%2FP5g3mM07iELNw%3D%3D",
          "OHgEq3Xhth9g3mM07iELNw%3D%3D",
          "oMrQJTbwkI1g3mM07iELNw%3D%3D",
          "NKJr5TxzHx1g3mM07iELNw%3D%3D",
          "4ROGiavwbbRg3mM07iELNw%3D%3D",
          "9GNQoc0yZdVg3mM07iELNw%3D%3D",
          "jRQTDVKt2Itg3mM07iELNw%3D%3D",
          "0KCGTin%2BsNNg3mM07iELNw%3D%3D",
          "7OfMVXLB6%2FNg3mM07iELNw%3D%3D",
          "Z7tiaOHUdrFg3mM07iELNw%3D%3D",
          "D%2FsA244J1fJg3mM07iELNw%3D%3D",
          "Y7U7H9aYpgNg3mM07iELNw%3D%3D",
          "oxOj7JBTbARg3mM07iELNw%3D%3D",
          "JwGmWbsT1oBg3mM07iELNw%3D%3D",
          "1L%2F14%2BQoalNg3mM07iELNw%3D%3D",
          "KgoW%2BdSUda1g3mM07iELNw%3D%3D",
          "DEjqXgqsp0Vg3mM07iELNw%3D%3D",
          "KSORJTXQrwxg3mM07iELNw%3D%3D",
          "ZoNQ0XzP6aNg3mM07iELNw%3D%3D",
          "QmGBH2NIRXhg3mM07iELNw%3D%3D",
          "c2451IOVFrJg3mM07iELNw%3D%3D",
          "Jifn8OT9duNg3mM07iELNw%3D%3D",
          "SIezvjJD%2Fztg3mM07iELNw%3D%3D",
          "Sm1ksgmEW%2BFg3mM07iELNw%3D%3D",
          "kywEJ%2B%2FG%2Fdlg3mM07iELNw%3D%3D",
          "ULSLxhgb%2BHRg3mM07iELNw%3D%3D",
          "BkH%2F40mblrNg3mM07iELNw%3D%3D",
          "Hs0jNALrErRg3mM07iELNw%3D%3D",
          "1UGYt%2BNOAOFg3mM07iELNw%3D%3D",
          "YCt9AbOliPlg3mM07iELNw%3D%3D",
          "jiyk5HJylfdg3mM07iELNw%3D%3D",
          "AlNgXMgitgVg3mM07iELNw%3D%3D",
          "DYfpugvFVaJg3mM07iELNw%3D%3D",
          "DYnB13JUiVJg3mM07iELNw%3D%3D",
          "dfgcKOBH%2B6dg3mM07iELNw%3D%3D",
          "3Uew26jzdZhg3mM07iELNw%3D%3D",
          "r%2F06Emgq7wRg3mM07iELNw%3D%3D",
          "B4lrQXBcdUdg3mM07iELNw%3D%3D"
        ],
        "title": "Lote 1"
      }
    ],
    "awardPeriod": {
      "endDate": null,
      "startDate": "2016-01-19T09:00:00-05:00"
    }
  },
  "packageInfo": {
    "publishedDate": "2017-10-10T10:47:04-04:00",
    "uri": "https://www.contrataciones.gov.py/datos/record-package/274744.json",
    "publisher": {
      "legalName": "Dirección Nacional de Contrataciones Públicas, Paraguay",
      "uri": "https://contrataciones.gov.py/datos",
      "name": "DNCP - Paraguay"
    }
  },
  "buyer": {
    "contactPoint": {
      "telephone": "021444142",
      "email": "uoc@copaco.com.py",
      "name": "Norma Beatriz Fernández de Burgos"
    },
    "name": "Compañía Paraguaya de Comunicaciones (COPACO)"
  }
}